[
    {
        "user": "U0606SPN4BW",
        "type": "message",
        "ts": "1751613490.927219",
        "client_msg_id": "d8b98657-723f-4ffd-bfef-d741977a59dc",
        "text": "<@U08U8MMTH43> <!subteam^S073HEMKWV7|@hirakawa-adachi-yamamoto-fuse>\nサンプル作成、撮影ありがとうございました！\n\n&gt; _※後日のサンプル発送時は、各1点ずつでよろしかったでしょうか。_\n・ラベルの枚数的に最大で何個づつ作成可能でしょうか？\n　念の為、ご確認をお願いいたします！",
        "team": "T033D70RR6H",
        "user_team": "T033D70RR6H",
        "source_team": "T033D70RR6H",
        "user_profile": {
            "avatar_hash": "823d8545f678",
            "image_72": "https:\/\/avatars.slack-edge.com\/2024-04-12\/6946592133062_823d8545f678615a3e0a_72.jpg",
            "first_name": "SATOSHI",
            "real_name": "SATOSHI FURUKAWA",
            "display_name": "古川　敏",
            "team": "T033D70RR6H",
            "name": "jpfreebirds",
            "is_restricted": false,
            "is_ultra_restricted": false
        },
        "thread_ts": "1751330379.036569",
        "parent_user_id": "U08U8MMTH43",
        "blocks": [
            {
                "type": "rich_text",
                "block_id": "XK5rS",
                "elements": [
                    {
                        "type": "rich_text_section",
                        "elements": [
                            {
                                "type": "user",
                                "user_id": "U08U8MMTH43"
                            },
                            {
                                "type": "text",
                                "text": " "
                            },
                            {
                                "type": "usergroup",
                                "usergroup_id": "S073HEMKWV7"
                            },
                            {
                                "type": "text",
                                "text": "\nサンプル作成、撮影ありがとうございました！\n\n"
                            }
                        ]
                    },
                    {
                        "type": "rich_text_quote",
                        "elements": [
                            {
                                "type": "text",
                                "text": "※後日のサンプル発送時は、各1点ずつでよろしかったでしょうか。",
                                "style": {
                                    "italic": true
                                }
                            }
                        ]
                    },
                    {
                        "type": "rich_text_section",
                        "elements": [
                            {
                                "type": "text",
                                "text": "・ラベルの枚数的に最大で何個づつ作成可能でしょうか？\n　念の為、ご確認をお願いいたします！"
                            }
                        ]
                    }
                ]
            }
        ]
    },
    {
        "user": "U08U8MMTH43",
        "type": "message",
        "ts": "1751618956.563259",
        "client_msg_id": "7a044207-58d7-485c-b5b8-a9f5e85f223a",
        "text": "<@U0606SPN4BW>\n<!subteam^S073HEMKWV7|@hirakawa-adachi-yamamoto-fuse>\nラベルは３枚ずつあります。\n貼りロスなければ最大3缶です。",
        "team": "T033D70RR6H",
        "user_team": "T033D70RR6H",
        "source_team": "T033D70RR6H",
        "user_profile": {
            "avatar_hash": "22a826d23669",
            "image_72": "https:\/\/avatars.slack-edge.com\/2025-05-28\/8954451860855_22a826d236694d5f657b_72.png",
            "first_name": "fuse",
            "real_name": "fuse",
            "display_name": "布施美穂",
            "team": "T033D70RR6H",
            "name": "tousuien.fuse",
            "is_restricted": false,
            "is_ultra_restricted": false
        },
        "thread_ts": "1751330379.036569",
        "parent_user_id": "U08U8MMTH43",
        "blocks": [
            {
                "type": "rich_text",
                "block_id": "tj1lC",
                "elements": [
                    {
                        "type": "rich_text_section",
                        "elements": [
                            {
                                "type": "user",
                                "user_id": "U0606SPN4BW"
                            },
                            {
                                "type": "text",
                                "text": "\n"
                            },
                            {
                                "type": "usergroup",
                                "usergroup_id": "S073HEMKWV7"
                            },
                            {
                                "type": "text",
                                "text": "\nラベルは３枚ずつあります。\n貼りロスなければ最大3缶です。"
                            }
                        ]
                    }
                ]
            }
        ],
        "reactions": [
            {
                "name": "d130b000eb8d6784",
                "users": [
                    "U0606SPN4BW"
                ],
                "count": 1
            },
            {
                "name": "承知-1",
                "users": [
                    "U0606SPN4BW"
                ],
                "count": 1
            }
        ]
    }
]