[
    {
        "user": "U0331FWGQRM",
        "type": "message",
        "ts": "1748855627.226419",
        "client_msg_id": "506d0ec1-2ac6-4f0b-a157-802447c08176",
        "text": "<@U0331FZS7JT>\n2025年の商品原価についてメモ",
        "team": "T033D70RR6H",
        "user_team": "T033D70RR6H",
        "source_team": "T033D70RR6H",
        "user_profile": {
            "avatar_hash": "gf9d05f2cae1",
            "image_72": "https:\/\/secure.gravatar.com\/avatar\/f9d05f2cae161f657bb1248fc85b5235.jpg?s=72&d=https%3A%2F%2Fa.slack-edge.com%2Fdf10d%2Fimg%2Favatars%2Fava_0008-72.png",
            "first_name": "matsui",
            "real_name": "matsui",
            "display_name": "松井",
            "team": "T033D70RR6H",
            "name": "tousuien.matsui",
            "is_restricted": false,
            "is_ultra_restricted": false
        },
        "thread_ts": "1748855627.226419",
        "reply_count": 1,
        "reply_users_count": 1,
        "latest_reply": "1748856109.260419",
        "reply_users": [
            "U0331FWGQRM"
        ],
        "replies": [
            {
                "user": "U0331FWGQRM",
                "ts": "1748856109.260419"
            }
        ],
        "is_locked": false,
        "subscribed": true,
        "last_read": "1748856109.260419",
        "blocks": [
            {
                "type": "rich_text",
                "block_id": "zIkKg",
                "elements": [
                    {
                        "type": "rich_text_section",
                        "elements": [
                            {
                                "type": "user",
                                "user_id": "U0331FZS7JT"
                            },
                            {
                                "type": "text",
                                "text": "\n2025年の商品原価についてメモ"
                            }
                        ]
                    }
                ]
            }
        ]
    },
    {
        "user": "U0331FWGQRM",
        "type": "message",
        "ts": "1748856109.260419",
        "edited": {
            "user": "U0331FWGQRM",
            "ts": "1748856143.000000"
        },
        "client_msg_id": "c05ed46a-d65d-42d0-b21e-408a3b9a34f8",
        "text": "<@U0331FZS7JT>\n抹茶の原料原価が1.5-1.8倍になる見込みです。\n香料については価格の上昇はありません。\n従いまして、商品価格としては26%-40%ほど上昇する見込み\n正確な抹茶原料の価格は6月半ばにわかりますので、現時点では正確な商品価格は未定です。\nつきましては、今回送付させていただくquotationの価格は2024年の抹茶価格で見積もりしております。\n\n全ての上昇価格を貴社に負担いただくつもりはありませんので、原価上昇26%-40%のうち、10%-15%は弊社で負担できるように努めたいと考えております。\nquotationの価格から、15%-25%ほど上昇した価格が最終売価になるとと思いますので、ご参考によろしくお願いします。",
        "team": "T033D70RR6H",
        "user_team": "T033D70RR6H",
        "source_team": "T033D70RR6H",
        "user_profile": {
            "avatar_hash": "gf9d05f2cae1",
            "image_72": "https:\/\/secure.gravatar.com\/avatar\/f9d05f2cae161f657bb1248fc85b5235.jpg?s=72&d=https%3A%2F%2Fa.slack-edge.com%2Fdf10d%2Fimg%2Favatars%2Fava_0008-72.png",
            "first_name": "matsui",
            "real_name": "matsui",
            "display_name": "松井",
            "team": "T033D70RR6H",
            "name": "tousuien.matsui",
            "is_restricted": false,
            "is_ultra_restricted": false
        },
        "thread_ts": "1748855627.226419",
        "parent_user_id": "U0331FWGQRM",
        "blocks": [
            {
                "type": "rich_text",
                "block_id": "d5yIR",
                "elements": [
                    {
                        "type": "rich_text_section",
                        "elements": [
                            {
                                "type": "user",
                                "user_id": "U0331FZS7JT"
                            },
                            {
                                "type": "text",
                                "text": "\n抹茶の原料原価が1.5-1.8倍になる見込みです。\n香料については価格の上昇はありません。\n従いまして、商品価格としては26%-40%ほど上昇する見込み\n正確な抹茶原料の価格は6月半ばにわかりますので、現時点では正確な商品価格は未定です。\nつきましては、今回送付させていただくquotationの価格は2024年の抹茶価格で見積もりしております。\n\n全ての上昇価格を貴社に負担いただくつもりはありませんので、原価上昇26%-40%のうち、10%-15%は弊社で負担できるように努めたいと考えております。\nquotationの価格から、15%-25%ほど上昇した価格が最終売価になるとと思いますので、ご参考によろしくお願いします。"
                            }
                        ]
                    }
                ]
            }
        ]
    },
    {
        "user": "U0331FZS7JT",
        "type": "message",
        "ts": "1748856846.790349",
        "client_msg_id": "a5ca76dd-820b-45ad-ba9f-06bb8935e4d0",
        "text": "メモ\n抹茶使用量\nPure 5000bags：305kg\nVanilla 5000bags：244kg\nCinnamon1,500 bags：74kg\nCoconut Raspberry1,500 bags：65kg\n200g 500 bags：100kg\n\n▼June-Oct + Dec\n月間：788kg\n合計：4,328kg\n\n▼Nov\n月間：1,237kg\n\n6-12月\n合計：5,565kg\n※但し、別途の注文やMango, Chaiは加味していない。",
        "team": "T033D70RR6H",
        "user_team": "T033D70RR6H",
        "source_team": "T033D70RR6H",
        "user_profile": {
            "avatar_hash": "2c9de1514f26",
            "image_72": "https:\/\/avatars.slack-edge.com\/2022-02-16\/3118160981555_2c9de1514f262063f72d_72.png",
            "first_name": "Yuta",
            "real_name": "Yuta Oka",
            "display_name": "岡祐太",
            "team": "T033D70RR6H",
            "name": "yuta.oka.0915",
            "is_restricted": false,
            "is_ultra_restricted": false
        },
        "thread_ts": "1748509294.946229",
        "parent_user_id": "U0331FWGQRM",
        "blocks": [
            {
                "type": "rich_text",
                "block_id": "r6uuO",
                "elements": [
                    {
                        "type": "rich_text_section",
                        "elements": [
                            {
                                "type": "text",
                                "text": "メモ\n抹茶使用量\nPure 5000bags：305kg\nVanilla 5000bags：244kg\nCinnamon1,500 bags：74kg\nCoconut Raspberry1,500 bags：65kg\n200g 500 bags：100kg\n\n▼June-Oct + Dec\n月間：788kg\n合計：4,328kg\n\n▼Nov\n月間：1,237kg\n\n6-12月\n合計：5,565kg\n※但し、別途の注文やMango, Chaiは加味していない。"
                            }
                        ]
                    }
                ]
            }
        ]
    },
    {
        "user": "U0331FWGQRM",
        "type": "message",
        "ts": "1748908658.534719",
        "client_msg_id": "226f70c9-ee99-4a9f-b609-f533610d3e19",
        "text": "<@U0331FZS7JT> <!subteam^S073HEMKWV7|@hirakawa-adachi-yamamoto-fuse> <!subteam^S088LEJ1U5T|@kanayama-fukui-miyoshi-yokoi-takuwa-hara-imaoka-agou>\n各香料の原料確保は大丈夫ですか？\n（数量把握＆購入スケジュールは立てていますか？）",
        "team": "T033D70RR6H",
        "user_team": "T033D70RR6H",
        "source_team": "T033D70RR6H",
        "user_profile": {
            "avatar_hash": "gf9d05f2cae1",
            "image_72": "https:\/\/secure.gravatar.com\/avatar\/f9d05f2cae161f657bb1248fc85b5235.jpg?s=72&d=https%3A%2F%2Fa.slack-edge.com%2Fdf10d%2Fimg%2Favatars%2Fava_0008-72.png",
            "first_name": "matsui",
            "real_name": "matsui",
            "display_name": "松井",
            "team": "T033D70RR6H",
            "name": "tousuien.matsui",
            "is_restricted": false,
            "is_ultra_restricted": false
        },
        "thread_ts": "1748509294.946229",
        "parent_user_id": "U0331FWGQRM",
        "blocks": [
            {
                "type": "rich_text",
                "block_id": "1SS1i",
                "elements": [
                    {
                        "type": "rich_text_section",
                        "elements": [
                            {
                                "type": "user",
                                "user_id": "U0331FZS7JT"
                            },
                            {
                                "type": "text",
                                "text": " "
                            },
                            {
                                "type": "usergroup",
                                "usergroup_id": "S073HEMKWV7"
                            },
                            {
                                "type": "text",
                                "text": " "
                            },
                            {
                                "type": "usergroup",
                                "usergroup_id": "S088LEJ1U5T"
                            },
                            {
                                "type": "text",
                                "text": "\n各香料の原料確保は大丈夫ですか？\n（数量把握＆購入スケジュールは立てていますか？）"
                            }
                        ]
                    }
                ]
            }
        ]
    },
    {
        "subtype": "channel_join",
        "user": "U08V56G9U92",
        "text": "<@U08V56G9U92>さんがチャンネルに参加しました",
        "type": "message",
        "ts": "1748914893.704939"
    }
]