[
    {
        "subtype": "channel_join",
        "user": "U0331FWGQRM",
        "text": "<@U0331FWGQRM>さんがチャンネルに参加しました",
        "type": "message",
        "ts": "1720992358.826059"
    },
    {
        "subtype": "channel_join",
        "user": "U0331FZS7JT",
        "text": "<@U0331FZS7JT>さんがチャンネルに参加しました",
        "inviter": "U0331FWGQRM",
        "type": "message",
        "ts": "1720992361.311099"
    },
    {
        "subtype": "channel_join",
        "user": "U0331FZTHEK",
        "text": "<@U0331FZTHEK>さんがチャンネルに参加しました",
        "inviter": "U0331FWGQRM",
        "type": "message",
        "ts": "1720992361.380859"
    },
    {
        "subtype": "channel_join",
        "user": "U033G4KN4TD",
        "text": "<@U033G4KN4TD>さんがチャンネルに参加しました",
        "inviter": "U0331FWGQRM",
        "type": "message",
        "ts": "1720992361.440689"
    },
    {
        "subtype": "channel_join",
        "user": "U03BLQ65GK0",
        "text": "<@U03BLQ65GK0>さんがチャンネルに参加しました",
        "inviter": "U0331FWGQRM",
        "type": "message",
        "ts": "1720992361.686489"
    },
    {
        "subtype": "channel_join",
        "user": "U041RJKV5JA",
        "text": "<@U041RJKV5JA>さんがチャンネルに参加しました",
        "inviter": "U0331FWGQRM",
        "type": "message",
        "ts": "1720992361.761429"
    },
    {
        "subtype": "channel_join",
        "user": "U05KGS6HN9H",
        "text": "<@U05KGS6HN9H>さんがチャンネルに参加しました",
        "inviter": "U0331FWGQRM",
        "type": "message",
        "ts": "1720992361.838699"
    },
    {
        "subtype": "channel_join",
        "user": "U0606SPN4BW",
        "text": "<@U0606SPN4BW>さんがチャンネルに参加しました",
        "inviter": "U0331FWGQRM",
        "type": "message",
        "ts": "1720992361.912779"
    },
    {
        "subtype": "channel_join",
        "user": "U066P20UQH1",
        "text": "<@U066P20UQH1>さんがチャンネルに参加しました",
        "inviter": "U0331FWGQRM",
        "type": "message",
        "ts": "1720992362.013079"
    },
    {
        "user": "U0331FWGQRM",
        "type": "message",
        "ts": "1720992425.689199",
        "edited": {
            "user": "U0331FWGQRM",
            "ts": "1720992697.000000"
        },
        "client_msg_id": "ae2ab26a-1f3a-4e6b-a93c-2640cb5050cc",
        "text": "*Sachet*\n(\/10g)\nMatcha　40%\nBeet sugar　50%\nWasanbon　10%",
        "team": "T033D70RR6H",
        "user_team": "T033D70RR6H",
        "source_team": "T033D70RR6H",
        "user_profile": {
            "avatar_hash": "gf9d05f2cae1",
            "image_72": "https:\/\/secure.gravatar.com\/avatar\/f9d05f2cae161f657bb1248fc85b5235.jpg?s=72&d=https%3A%2F%2Fa.slack-edge.com%2Fdf10d%2Fimg%2Favatars%2Fava_0008-72.png",
            "first_name": "matsui",
            "real_name": "matsui",
            "display_name": "松井",
            "team": "T033D70RR6H",
            "name": "tousuien.matsui",
            "is_restricted": false,
            "is_ultra_restricted": false
        },
        "thread_ts": "1720992425.689199",
        "reply_count": 15,
        "reply_users_count": 2,
        "latest_reply": "1723018005.123269",
        "reply_users": [
            "U0331FWGQRM",
            "U041RJKV5JA"
        ],
        "replies": [
            {
                "user": "U0331FWGQRM",
                "ts": "1720992596.502119"
            },
            {
                "user": "U041RJKV5JA",
                "ts": "1721298133.163949"
            },
            {
                "user": "U0331FWGQRM",
                "ts": "1721325223.264279"
            },
            {
                "user": "U041RJKV5JA",
                "ts": "1721824314.232949"
            },
            {
                "user": "U0331FWGQRM",
                "ts": "1721867023.880679"
            },
            {
                "user": "U041RJKV5JA",
                "ts": "1721868689.049769"
            },
            {
                "user": "U0331FWGQRM",
                "ts": "1721869589.650449"
            },
            {
                "user": "U041RJKV5JA",
                "ts": "1721884997.340239"
            },
            {
                "user": "U0331FWGQRM",
                "ts": "1721898527.820839"
            },
            {
                "user": "U041RJKV5JA",
                "ts": "1721963898.606999"
            },
            {
                "user": "U0331FWGQRM",
                "ts": "1721971971.931839"
            },
            {
                "user": "U041RJKV5JA",
                "ts": "1721972712.826739"
            },
            {
                "user": "U041RJKV5JA",
                "ts": "1722813659.126899"
            },
            {
                "user": "U0331FWGQRM",
                "ts": "1722849234.477369"
            },
            {
                "user": "U041RJKV5JA",
                "ts": "1723018005.123269"
            }
        ],
        "is_locked": false,
        "subscribed": true,
        "last_read": "1723018005.123269",
        "blocks": [
            {
                "type": "rich_text",
                "block_id": "KRK6j",
                "elements": [
                    {
                        "type": "rich_text_section",
                        "elements": [
                            {
                                "type": "text",
                                "text": "Sachet",
                                "style": {
                                    "bold": true
                                }
                            },
                            {
                                "type": "text",
                                "text": "\n(\/10g)\nMatcha　40%\nBeet sugar　50%\nWasanbon　10%"
                            }
                        ]
                    }
                ]
            }
        ]
    },
    {
        "text": "<!subteam^S073HEMKWV7|@hirakawa-adachi-yamamoto-fuse>\nブレンド比率（上記）は未定ですが、おそらくこのぐらいの比率になります。\nSachetのダイライン（デザインのフォーマット）を入手するために、\nSachetのサイズを確定する必要があります。\n原料サンプルを吉村に送って、sachetのサイズを決めてもらえますか？\nMomatchaは添付のsachetをイメージしていたので、この感じをベースにしてもらえますか？\n\n※添付画像は、形状を参考にしてくださいという意味であって、\n　寸法はこちらで設定してOKです。（むしろ提案してくださいとのことです）",
        "files": [
            {
                "id": "F07CD3L2H26",
                "created": 1720992567,
                "timestamp": 1720992567,
                "name": "45B7378CE32E7722BE074744C174392F (1).jpg",
                "title": "45B7378CE32E7722BE074744C174392F (1).jpg",
                "mimetype": "image\/jpeg",
                "filetype": "jpg",
                "pretty_type": "JPEG",
                "user": "U0331FWGQRM",
                "user_team": "T033D70RR6H",
                "editable": false,
                "size": 95773,
                "mode": "hosted",
                "is_external": false,
                "external_type": "",
                "is_public": true,
                "public_url_shared": false,
                "display_as_bot": false,
                "username": "",
                "url_private": "https:\/\/files.slack.com\/files-pri\/T033D70RR6H-F07CD3L2H26\/45b7378ce32e7722be074744c174392f__1_.jpg?token=xoxe-3115238875221-9710624591398-9697214945543-aa82359f925d11baadb4ddc07b089467",
                "url_private_download": "https:\/\/files.slack.com\/files-pri\/T033D70RR6H-F07CD3L2H26\/download\/45b7378ce32e7722be074744c174392f__1_.jpg?token=xoxe-3115238875221-9710624591398-9697214945543-aa82359f925d11baadb4ddc07b089467",
                "media_display_type": "unknown",
                "thumb_64": "https:\/\/files.slack.com\/files-tmb\/T033D70RR6H-F07CD3L2H26-9574f8c6f4\/45b7378ce32e7722be074744c174392f__1__64.jpg?t=xoxe-3115238875221-9710624591398-9697214945543-aa82359f925d11baadb4ddc07b089467",
                "thumb_80": "https:\/\/files.slack.com\/files-tmb\/T033D70RR6H-F07CD3L2H26-9574f8c6f4\/45b7378ce32e7722be074744c174392f__1__80.jpg?t=xoxe-3115238875221-9710624591398-9697214945543-aa82359f925d11baadb4ddc07b089467",
                "thumb_360": "https:\/\/files.slack.com\/files-tmb\/T033D70RR6H-F07CD3L2H26-9574f8c6f4\/45b7378ce32e7722be074744c174392f__1__360.jpg?t=xoxe-3115238875221-9710624591398-9697214945543-aa82359f925d11baadb4ddc07b089467",
                "thumb_360_w": 360,
                "thumb_360_h": 289,
                "thumb_480": "https:\/\/files.slack.com\/files-tmb\/T033D70RR6H-F07CD3L2H26-9574f8c6f4\/45b7378ce32e7722be074744c174392f__1__480.jpg?t=xoxe-3115238875221-9710624591398-9697214945543-aa82359f925d11baadb4ddc07b089467",
                "thumb_480_w": 480,
                "thumb_480_h": 385,
                "thumb_160": "https:\/\/files.slack.com\/files-tmb\/T033D70RR6H-F07CD3L2H26-9574f8c6f4\/45b7378ce32e7722be074744c174392f__1__160.jpg?t=xoxe-3115238875221-9710624591398-9697214945543-aa82359f925d11baadb4ddc07b089467",
                "thumb_720": "https:\/\/files.slack.com\/files-tmb\/T033D70RR6H-F07CD3L2H26-9574f8c6f4\/45b7378ce32e7722be074744c174392f__1__720.jpg?t=xoxe-3115238875221-9710624591398-9697214945543-aa82359f925d11baadb4ddc07b089467",
                "thumb_720_w": 720,
                "thumb_720_h": 577,
                "thumb_800": "https:\/\/files.slack.com\/files-tmb\/T033D70RR6H-F07CD3L2H26-9574f8c6f4\/45b7378ce32e7722be074744c174392f__1__800.jpg?t=xoxe-3115238875221-9710624591398-9697214945543-aa82359f925d11baadb4ddc07b089467",
                "thumb_800_w": 800,
                "thumb_800_h": 641,
                "thumb_960": "https:\/\/files.slack.com\/files-tmb\/T033D70RR6H-F07CD3L2H26-9574f8c6f4\/45b7378ce32e7722be074744c174392f__1__960.jpg?t=xoxe-3115238875221-9710624591398-9697214945543-aa82359f925d11baadb4ddc07b089467",
                "thumb_960_w": 960,
                "thumb_960_h": 770,
                "thumb_1024": "https:\/\/files.slack.com\/files-tmb\/T033D70RR6H-F07CD3L2H26-9574f8c6f4\/45b7378ce32e7722be074744c174392f__1__1024.jpg?t=xoxe-3115238875221-9710624591398-9697214945543-aa82359f925d11baadb4ddc07b089467",
                "thumb_1024_w": 1024,
                "thumb_1024_h": 821,
                "original_w": 1080,
                "original_h": 866,
                "thumb_tiny": "AwAmADDTooooAqys\/msA7D2FEDM0oy7EehqG9fbOy7tuQOcUae5MrKWLADOT2qNblX0NCiiirJCiiigDPul33DAruAAOO1OsxtmKhNvBNOmdkncqARgZzS2rs7ZYYqb6l9C3RRRVEBRRRQBUmDecxGPzohz5wPH50sv+sali\/wBYKm2ppbQs0UUVRmf\/2Q==",
                "permalink": "https:\/\/grp-ssm9297.slack.com\/files\/U0331FWGQRM\/F07CD3L2H26\/45b7378ce32e7722be074744c174392f__1_.jpg",
                "permalink_public": "https:\/\/slack-files.com\/T033D70RR6H-F07CD3L2H26-a5556deb33",
                "is_starred": false,
                "skipped_shares": true,
                "has_rich_preview": false,
                "file_access": "visible"
            },
            {
                "id": "F07CRP29Z9P",
                "created": 1720992569,
                "timestamp": 1720992569,
                "name": "FE25D10346EBCBC191E2255FACC8A3D5.jpg",
                "title": "FE25D10346EBCBC191E2255FACC8A3D5.jpg",
                "mimetype": "image\/jpeg",
                "filetype": "jpg",
                "pretty_type": "JPEG",
                "user": "U0331FWGQRM",
                "user_team": "T033D70RR6H",
                "editable": false,
                "size": 59165,
                "mode": "hosted",
                "is_external": false,
                "external_type": "",
                "is_public": true,
                "public_url_shared": false,
                "display_as_bot": false,
                "username": "",
                "url_private": "https:\/\/files.slack.com\/files-pri\/T033D70RR6H-F07CRP29Z9P\/fe25d10346ebcbc191e2255facc8a3d5.jpg?token=xoxe-3115238875221-9710624591398-9697214945543-aa82359f925d11baadb4ddc07b089467",
                "url_private_download": "https:\/\/files.slack.com\/files-pri\/T033D70RR6H-F07CRP29Z9P\/download\/fe25d10346ebcbc191e2255facc8a3d5.jpg?token=xoxe-3115238875221-9710624591398-9697214945543-aa82359f925d11baadb4ddc07b089467",
                "media_display_type": "unknown",
                "thumb_64": "https:\/\/files.slack.com\/files-tmb\/T033D70RR6H-F07CRP29Z9P-276f75e8c6\/fe25d10346ebcbc191e2255facc8a3d5_64.jpg?t=xoxe-3115238875221-9710624591398-9697214945543-aa82359f925d11baadb4ddc07b089467",
                "thumb_80": "https:\/\/files.slack.com\/files-tmb\/T033D70RR6H-F07CRP29Z9P-276f75e8c6\/fe25d10346ebcbc191e2255facc8a3d5_80.jpg?t=xoxe-3115238875221-9710624591398-9697214945543-aa82359f925d11baadb4ddc07b089467",
                "thumb_360": "https:\/\/files.slack.com\/files-tmb\/T033D70RR6H-F07CRP29Z9P-276f75e8c6\/fe25d10346ebcbc191e2255facc8a3d5_360.jpg?t=xoxe-3115238875221-9710624591398-9697214945543-aa82359f925d11baadb4ddc07b089467",
                "thumb_360_w": 360,
                "thumb_360_h": 280,
                "thumb_480": "https:\/\/files.slack.com\/files-tmb\/T033D70RR6H-F07CRP29Z9P-276f75e8c6\/fe25d10346ebcbc191e2255facc8a3d5_480.jpg?t=xoxe-3115238875221-9710624591398-9697214945543-aa82359f925d11baadb4ddc07b089467",
                "thumb_480_w": 480,
                "thumb_480_h": 373,
                "thumb_160": "https:\/\/files.slack.com\/files-tmb\/T033D70RR6H-F07CRP29Z9P-276f75e8c6\/fe25d10346ebcbc191e2255facc8a3d5_160.jpg?t=xoxe-3115238875221-9710624591398-9697214945543-aa82359f925d11baadb4ddc07b089467",
                "thumb_720": "https:\/\/files.slack.com\/files-tmb\/T033D70RR6H-F07CRP29Z9P-276f75e8c6\/fe25d10346ebcbc191e2255facc8a3d5_720.jpg?t=xoxe-3115238875221-9710624591398-9697214945543-aa82359f925d11baadb4ddc07b089467",
                "thumb_720_w": 720,
                "thumb_720_h": 560,
                "thumb_800": "https:\/\/files.slack.com\/files-tmb\/T033D70RR6H-F07CRP29Z9P-276f75e8c6\/fe25d10346ebcbc191e2255facc8a3d5_800.jpg?t=xoxe-3115238875221-9710624591398-9697214945543-aa82359f925d11baadb4ddc07b089467",
                "thumb_800_w": 800,
                "thumb_800_h": 622,
                "thumb_960": "https:\/\/files.slack.com\/files-tmb\/T033D70RR6H-F07CRP29Z9P-276f75e8c6\/fe25d10346ebcbc191e2255facc8a3d5_960.jpg?t=xoxe-3115238875221-9710624591398-9697214945543-aa82359f925d11baadb4ddc07b089467",
                "thumb_960_w": 960,
                "thumb_960_h": 747,
                "thumb_1024": "https:\/\/files.slack.com\/files-tmb\/T033D70RR6H-F07CRP29Z9P-276f75e8c6\/fe25d10346ebcbc191e2255facc8a3d5_1024.jpg?t=xoxe-3115238875221-9710624591398-9697214945543-aa82359f925d11baadb4ddc07b089467",
                "thumb_1024_w": 1024,
                "thumb_1024_h": 796,
                "original_w": 1080,
                "original_h": 840,
                "thumb_tiny": "AwAlADDTooooAr3CAtk56etJbx4kzlunrUkvWmwsPNK46CptqVd2sT0UUVRIUUUUARTUkP3j9KjvfN2jyc5zzUdkZ\/NIlB27fSpsMvUUUVQgooooAqzu3mFeMe4otyfMxgYPoKbP\/rmpbf8A1oqeptyrluW6KKKoxP\/Z",
                "permalink": "https:\/\/grp-ssm9297.slack.com\/files\/U0331FWGQRM\/F07CRP29Z9P\/fe25d10346ebcbc191e2255facc8a3d5.jpg",
                "permalink_public": "https:\/\/slack-files.com\/T033D70RR6H-F07CRP29Z9P-c8fd4bd5e5",
                "is_starred": false,
                "skipped_shares": true,
                "has_rich_preview": false,
                "file_access": "visible"
            }
        ],
        "upload": false,
        "user": "U0331FWGQRM",
        "blocks": [
            {
                "type": "rich_text",
                "block_id": "6vWHD",
                "elements": [
                    {
                        "type": "rich_text_section",
                        "elements": [
                            {
                                "type": "usergroup",
                                "usergroup_id": "S073HEMKWV7"
                            },
                            {
                                "type": "text",
                                "text": "\nブレンド比率（上記）は未定ですが、おそらくこのぐらいの比率になります。\nSachetのダイライン（デザインのフォーマット）を入手するために、\nSachetのサイズを確定する必要があります。\n原料サンプルを吉村に送って、sachetのサイズを決めてもらえますか？\nMomatchaは添付のsachetをイメージしていたので、この感じをベースにしてもらえますか？\n\n※添付画像は、形状を参考にしてくださいという意味であって、\n　寸法はこちらで設定してOKです。（むしろ提案してくださいとのことです）"
                            }
                        ]
                    }
                ]
            }
        ],
        "type": "message",
        "ts": "1720992596.502119",
        "edited": {
            "user": "U0331FWGQRM",
            "ts": "1720992645.000000"
        },
        "client_msg_id": "ef7ecec0-3f30-407e-968a-177f6ff5ea79",
        "thread_ts": "1720992425.689199",
        "parent_user_id": "U0331FWGQRM",
        "reactions": [
            {
                "name": "承知_致しました",
                "users": [
                    "U041RJKV5JA"
                ],
                "count": 1
            }
        ]
    },
    {
        "user": "U0331FWGQRM",
        "type": "message",
        "ts": "1720992763.667529",
        "client_msg_id": "5d0700f5-ba44-496d-b5cf-a389bcdf4688",
        "text": "*Ceremoanial grade KIWAMI matcha 30g pull top type tin (bag in tin)*",
        "team": "T033D70RR6H",
        "user_team": "T033D70RR6H",
        "source_team": "T033D70RR6H",
        "user_profile": {
            "avatar_hash": "gf9d05f2cae1",
            "image_72": "https:\/\/secure.gravatar.com\/avatar\/f9d05f2cae161f657bb1248fc85b5235.jpg?s=72&d=https%3A%2F%2Fa.slack-edge.com%2Fdf10d%2Fimg%2Favatars%2Fava_0008-72.png",
            "first_name": "matsui",
            "real_name": "matsui",
            "display_name": "松井",
            "team": "T033D70RR6H",
            "name": "tousuien.matsui",
            "is_restricted": false,
            "is_ultra_restricted": false
        },
        "thread_ts": "1720992763.667529",
        "reply_count": 3,
        "reply_users_count": 2,
        "latest_reply": "1721142819.867199",
        "reply_users": [
            "U0331FWGQRM",
            "U05KGS6HN9H"
        ],
        "replies": [
            {
                "user": "U0331FWGQRM",
                "ts": "1720992852.198579"
            },
            {
                "user": "U05KGS6HN9H",
                "ts": "1721090688.730259"
            },
            {
                "user": "U0331FWGQRM",
                "ts": "1721142819.867199"
            }
        ],
        "is_locked": false,
        "subscribed": true,
        "last_read": "1721142819.867199",
        "blocks": [
            {
                "type": "rich_text",
                "block_id": "1mSYG",
                "elements": [
                    {
                        "type": "rich_text_section",
                        "elements": [
                            {
                                "type": "text",
                                "text": "Ceremoanial grade KIWAMI matcha 30g pull top type tin (bag in tin)",
                                "style": {
                                    "bold": true
                                }
                            }
                        ]
                    }
                ]
            }
        ]
    },
    {
        "user": "U0331FWGQRM",
        "type": "message",
        "ts": "1720992852.198579",
        "edited": {
            "user": "U0331FWGQRM",
            "ts": "1720992861.000000"
        },
        "client_msg_id": "77715f07-d196-40ac-8ec9-42c083552de3",
        "text": "<!subteam^S073HEMKWV7|@hirakawa-adachi-yamamoto-fuse>\nラベルデザインがリニューアルされました。\nとりあえず、2000枚くらい印刷を進めます。\n\n※蓋のラベルは“変更なし” です。\n引き続き同じデザインを使用します。",
        "team": "T033D70RR6H",
        "user_team": "T033D70RR6H",
        "source_team": "T033D70RR6H",
        "user_profile": {
            "avatar_hash": "gf9d05f2cae1",
            "image_72": "https:\/\/secure.gravatar.com\/avatar\/f9d05f2cae161f657bb1248fc85b5235.jpg?s=72&d=https%3A%2F%2Fa.slack-edge.com%2Fdf10d%2Fimg%2Favatars%2Fava_0008-72.png",
            "first_name": "matsui",
            "real_name": "matsui",
            "display_name": "松井",
            "team": "T033D70RR6H",
            "name": "tousuien.matsui",
            "is_restricted": false,
            "is_ultra_restricted": false
        },
        "thread_ts": "1720992763.667529",
        "parent_user_id": "U0331FWGQRM",
        "blocks": [
            {
                "type": "rich_text",
                "block_id": "IwY9s",
                "elements": [
                    {
                        "type": "rich_text_section",
                        "elements": [
                            {
                                "type": "usergroup",
                                "usergroup_id": "S073HEMKWV7"
                            },
                            {
                                "type": "text",
                                "text": "\nラベルデザインがリニューアルされました。\nとりあえず、2000枚くらい印刷を進めます。\n\n※蓋のラベルは“変更なし” です。\n引き続き同じデザインを使用します。"
                            }
                        ]
                    }
                ]
            }
        ],
        "reactions": [
            {
                "name": "承知_致しました",
                "users": [
                    "U041RJKV5JA",
                    "U033G4KN4TD",
                    "U05KGS6HN9H"
                ],
                "count": 3
            }
        ]
    }
]