[
    {
        "user": "U05KGS6HN9H",
        "type": "message",
        "ts": "1750404111.761819",
        "client_msg_id": "e044b7b0-7c53-453b-9ee3-4e1744418a7f",
        "text": "<@U066P20UQH1>\n<!subteam^S073HEMKWV7|@hirakawa-adachi-yamamoto-fuse> <!subteam^S088LEJ1U5T|@kanayama-fukui-miyoshi-yokoi-takuwa-hara-imaoka-agou> <@U0606SPN4BW>\n50gラベル：桃翠園在庫276枚（新規手配頂いた分と合わせると476枚予定）\nクラフトbag（清和11555）在庫325枚、不足分は発注済みです（6\/24入荷予定）",
        "team": "T033D70RR6H",
        "user_team": "T033D70RR6H",
        "source_team": "T033D70RR6H",
        "user_profile": {
            "avatar_hash": "gc4e7258333f",
            "image_72": "https:\/\/secure.gravatar.com\/avatar\/c4e7258333f2958f831d063db85b4542.jpg?s=72&d=https%3A%2F%2Fa.slack-edge.com%2Fdf10d%2Fimg%2Favatars%2Fava_0005-72.png",
            "first_name": "Adachi",
            "real_name": "Adachi",
            "display_name": "足立",
            "team": "T033D70RR6H",
            "name": "tousuien05",
            "is_restricted": false,
            "is_ultra_restricted": false
        },
        "thread_ts": "1746084267.674049",
        "parent_user_id": "U066P20UQH1",
        "blocks": [
            {
                "type": "rich_text",
                "block_id": "ukJkI",
                "elements": [
                    {
                        "type": "rich_text_section",
                        "elements": [
                            {
                                "type": "user",
                                "user_id": "U066P20UQH1"
                            },
                            {
                                "type": "text",
                                "text": "\n"
                            },
                            {
                                "type": "usergroup",
                                "usergroup_id": "S073HEMKWV7"
                            },
                            {
                                "type": "text",
                                "text": " "
                            },
                            {
                                "type": "usergroup",
                                "usergroup_id": "S088LEJ1U5T"
                            },
                            {
                                "type": "text",
                                "text": " "
                            },
                            {
                                "type": "user",
                                "user_id": "U0606SPN4BW"
                            },
                            {
                                "type": "text",
                                "text": "\n50gラベル：桃翠園在庫276枚（新規手配頂いた分と合わせると476枚予定）\nクラフトbag（清和11555）在庫325枚、不足分は発注済みです（6\/24入荷予定）"
                            }
                        ]
                    }
                ]
            }
        ],
        "reactions": [
            {
                "name": "ありかとう",
                "users": [
                    "U066P20UQH1"
                ],
                "count": 1
            }
        ]
    },
    {
        "user": "U05KGS6HN9H",
        "type": "message",
        "ts": "1750405659.905539",
        "client_msg_id": "6ed17672-311f-4ac4-8394-eb680dfdea3f",
        "text": "<@U0606SPN4BW>\n<!subteam^S073HEMKWV7|@hirakawa-adachi-yamamoto-fuse> <!subteam^S072Q871SF9|@oka-matsui-furukawa-hayashi-kimura-hasegawa-kawatani> <@U066P20UQH1>\nペガサスさんに返送方法を伺いました。\n返送（日本側から見て輸入）の場合、桃翠園で通常使用しているシステムでは送り状作成が\n出来ない為、必要情報をペガサス側に伝えて送り状や返送の手配をお願いする方法となります。\nINVOICE記載内容以外に必要なオランダ現地側の情報もあるようですので、ペガサスから\nエクセル書式の情報入力ファイルをもらいましたら共有致します。これと合わせて、返送の\nINVOICEやPackingListをペガサスに送り段取りをお願いする予定です。\n取り急ぎまして現状までを連絡致します。",
        "team": "T033D70RR6H",
        "user_team": "T033D70RR6H",
        "source_team": "T033D70RR6H",
        "user_profile": {
            "avatar_hash": "gc4e7258333f",
            "image_72": "https:\/\/secure.gravatar.com\/avatar\/c4e7258333f2958f831d063db85b4542.jpg?s=72&d=https%3A%2F%2Fa.slack-edge.com%2Fdf10d%2Fimg%2Favatars%2Fava_0005-72.png",
            "first_name": "Adachi",
            "real_name": "Adachi",
            "display_name": "足立",
            "team": "T033D70RR6H",
            "name": "tousuien05",
            "is_restricted": false,
            "is_ultra_restricted": false
        },
        "thread_ts": "1746671028.965679",
        "parent_user_id": "U066P20UQH1",
        "blocks": [
            {
                "type": "rich_text",
                "block_id": "17rGQ",
                "elements": [
                    {
                        "type": "rich_text_section",
                        "elements": [
                            {
                                "type": "user",
                                "user_id": "U0606SPN4BW"
                            },
                            {
                                "type": "text",
                                "text": "\n"
                            },
                            {
                                "type": "usergroup",
                                "usergroup_id": "S073HEMKWV7"
                            },
                            {
                                "type": "text",
                                "text": " "
                            },
                            {
                                "type": "usergroup",
                                "usergroup_id": "S072Q871SF9"
                            },
                            {
                                "type": "text",
                                "text": " "
                            },
                            {
                                "type": "user",
                                "user_id": "U066P20UQH1"
                            },
                            {
                                "type": "text",
                                "text": "\nペガサスさんに返送方法を伺いました。\n返送（日本側から見て輸入）の場合、桃翠園で通常使用しているシステムでは送り状作成が\n出来ない為、必要情報をペガサス側に伝えて送り状や返送の手配をお願いする方法となります。\nINVOICE記載内容以外に必要なオランダ現地側の情報もあるようですので、ペガサスから\nエクセル書式の情報入力ファイルをもらいましたら共有致します。これと合わせて、返送の\nINVOICEやPackingListをペガサスに送り段取りをお願いする予定です。\n取り急ぎまして現状までを連絡致します。"
                            }
                        ]
                    }
                ]
            }
        ],
        "reactions": [
            {
                "name": "承知-1",
                "users": [
                    "U066P20UQH1",
                    "U0606SPN4BW"
                ],
                "count": 2
            },
            {
                "name": "d130b000eb8d6784",
                "users": [
                    "U066P20UQH1",
                    "U0606SPN4BW"
                ],
                "count": 2
            }
        ]
    },
    {
        "user": "U08U8MMTH43",
        "type": "message",
        "ts": "1750406606.042269",
        "edited": {
            "user": "U08U8MMTH43",
            "ts": "1750406671.000000"
        },
        "client_msg_id": "2480040c-58f6-4bbc-8115-08bdb8d748f9",
        "text": "<@U066P20UQH1>\n<!subteam^S073HEMKWV7|@hirakawa-adachi-yamamoto-fuse>\nTSE-MOM-012-25-2の原産地証明書取得の際に「Ceremonial」の綴りが違うと指摘が入ったたため、インボイス、パッキングリスト訂正しています。\nご確認お願いいたします。",
        "team": "T033D70RR6H",
        "user_team": "T033D70RR6H",
        "source_team": "T033D70RR6H",
        "user_profile": {
            "avatar_hash": "22a826d23669",
            "image_72": "https:\/\/avatars.slack-edge.com\/2025-05-28\/8954451860855_22a826d236694d5f657b_72.png",
            "first_name": "fuse",
            "real_name": "fuse",
            "display_name": "布施美穂",
            "team": "T033D70RR6H",
            "name": "tousuien.fuse",
            "is_restricted": false,
            "is_ultra_restricted": false
        },
        "thread_ts": "1748414455.603919",
        "parent_user_id": "U066P20UQH1",
        "blocks": [
            {
                "type": "rich_text",
                "block_id": "2uhes",
                "elements": [
                    {
                        "type": "rich_text_section",
                        "elements": [
                            {
                                "type": "user",
                                "user_id": "U066P20UQH1"
                            },
                            {
                                "type": "text",
                                "text": "\n"
                            },
                            {
                                "type": "usergroup",
                                "usergroup_id": "S073HEMKWV7"
                            },
                            {
                                "type": "text",
                                "text": "\nTSE-MOM-012-25-2の原産地証明書取得の際に「Ceremonial」の綴りが違うと指摘が入ったたため、インボイス、パッキングリスト訂正しています。\nご確認お願いいたします。"
                            }
                        ]
                    }
                ]
            }
        ],
        "reactions": [
            {
                "name": "すみません",
                "users": [
                    "U066P20UQH1"
                ],
                "count": 1
            },
            {
                "name": "ありかとう",
                "users": [
                    "U066P20UQH1"
                ],
                "count": 1
            },
            {
                "name": "sweat_drops",
                "users": [
                    "U066P20UQH1"
                ],
                "count": 1
            }
        ]
    },
    {
        "user": "U041RJKV5JA",
        "type": "message",
        "ts": "1750408843.921049",
        "client_msg_id": "b30a9754-1551-42b3-9264-c29708de8da6",
        "text": "<@U0331FZS7JT>\n <!subteam^S072Q871SF9|@oka-matsui-furukawa-hayashi-kimura-hasegawa-kawatani> <!subteam^S073HEMKWV7|@hirakawa-adachi-yamamoto-fuse>\nペガサスグローバルより、検疫の対象となった理由および検疫検査費用の請求がございました。\n オーストラリアへの輸出においては通常、検疫は不要であるため、今回の検査に関する費用請求には応じられない旨をUPSに伝えていただきましたが、受け入れられませんでした。\n 以下に、該当のメール本文を転記いたします。\n----------\nUPSからの回答としましてオーストラリアに限らず、\n検疫検査については検査証明書等の提出を必須にしていない品目についても不定期にて行われる場合があるため、\n毎回行う、検疫を行うことはない、というはっきりとした回答は得られにくい状況です。\nなお今回発生した費用については下記となります。\n現地検疫費用：￥31,690\n手数料：￥3,300\n計　￥34,990\nこれまでDHLでこのようなトラブルが無いようであれば、\n今後オーストラリアに抹茶を出される際はDHLでの輸送をご推奨いたします。\n\nまた新しい取引先（国）に発送される際は事前に弊社へご連絡いただけますでしょうか。\n現地DHL\/UPSの連絡先だけでもお調べさせていただきます。\n----------",
        "team": "T033D70RR6H",
        "user_team": "T033D70RR6H",
        "source_team": "T033D70RR6H",
        "user_profile": {
            "avatar_hash": "aed9eafd9eee",
            "image_72": "https:\/\/avatars.slack-edge.com\/2022-09-11\/4078874890257_aed9eafd9eee277ba076_72.png",
            "first_name": "Hirakawa",
            "real_name": "Hirakawa",
            "display_name": "平川",
            "team": "T033D70RR6H",
            "name": "tousuien.s006",
            "is_restricted": false,
            "is_ultra_restricted": false
        },
        "thread_ts": "1730177216.926669",
        "parent_user_id": "U0331FZS7JT",
        "blocks": [
            {
                "type": "rich_text",
                "block_id": "jnnM\/",
                "elements": [
                    {
                        "type": "rich_text_section",
                        "elements": [
                            {
                                "type": "user",
                                "user_id": "U0331FZS7JT"
                            },
                            {
                                "type": "text",
                                "text": "\n "
                            },
                            {
                                "type": "usergroup",
                                "usergroup_id": "S072Q871SF9"
                            },
                            {
                                "type": "text",
                                "text": " "
                            },
                            {
                                "type": "usergroup",
                                "usergroup_id": "S073HEMKWV7"
                            },
                            {
                                "type": "text",
                                "text": "\nペガサスグローバルより、検疫の対象となった理由および検疫検査費用の請求がございました。\n オーストラリアへの輸出においては通常、検疫は不要であるため、今回の検査に関する費用請求には応じられない旨をUPSに伝えていただきましたが、受け入れられませんでした。\n 以下に、該当のメール本文を転記いたします。\n----------\nUPSからの回答としましてオーストラリアに限らず、\n検疫検査については検査証明書等の提出を必須にしていない品目についても不定期にて行われる場合があるため、\n毎回行う、検疫を行うことはない、というはっきりとした回答は得られにくい状況です。\nなお今回発生した費用については下記となります。\n現地検疫費用：￥31,690\n手数料：￥3,300\n計　￥34,990\nこれまでDHLでこのようなトラブルが無いようであれば、\n今後オーストラリアに抹茶を出される際はDHLでの輸送をご推奨いたします。\n\nまた新しい取引先（国）に発送される際は事前に弊社へご連絡いただけますでしょうか。\n現地DHL\/UPSの連絡先だけでもお調べさせていただきます。\n----------"
                            }
                        ]
                    }
                ]
            }
        ],
        "reactions": [
            {
                "name": "了解です",
                "users": [
                    "U0331FZS7JT"
                ],
                "count": 1
            },
            {
                "name": "d130b000eb8d6784",
                "users": [
                    "U0331FZS7JT"
                ],
                "count": 1
            },
            {
                "name": "eyes",
                "users": [
                    "U0331FWGQRM"
                ],
                "count": 1
            }
        ]
    },
    {
        "user": "U0331FWGQRM",
        "type": "message",
        "ts": "1750410335.747159",
        "client_msg_id": "b2f40de8-a0fa-4c62-b32b-42d46c509999",
        "text": "<!subteam^S073HEMKWV7|@hirakawa-adachi-yamamoto-fuse>\n数量変更可能です。\n1kgへ変更依頼してみます。\n取り急ぎ。\n\n<@U03BLQ65GK0> <@U0331FZS7JT>\n今年入荷分は2kgと聞いてますが、\nそれは別途あるんですよね？",
        "team": "T033D70RR6H",
        "user_team": "T033D70RR6H",
        "source_team": "T033D70RR6H",
        "user_profile": {
            "avatar_hash": "gf9d05f2cae1",
            "image_72": "https:\/\/secure.gravatar.com\/avatar\/f9d05f2cae161f657bb1248fc85b5235.jpg?s=72&d=https%3A%2F%2Fa.slack-edge.com%2Fdf10d%2Fimg%2Favatars%2Fava_0008-72.png",
            "first_name": "matsui",
            "real_name": "matsui",
            "display_name": "松井",
            "team": "T033D70RR6H",
            "name": "tousuien.matsui",
            "is_restricted": false,
            "is_ultra_restricted": false
        },
        "thread_ts": "1749056559.829009",
        "parent_user_id": "U0331FWGQRM",
        "blocks": [
            {
                "type": "rich_text",
                "block_id": "e388\/",
                "elements": [
                    {
                        "type": "rich_text_section",
                        "elements": [
                            {
                                "type": "usergroup",
                                "usergroup_id": "S073HEMKWV7"
                            },
                            {
                                "type": "text",
                                "text": "\n数量変更可能です。\n1kgへ変更依頼してみます。\n取り急ぎ。\n\n"
                            },
                            {
                                "type": "user",
                                "user_id": "U03BLQ65GK0"
                            },
                            {
                                "type": "text",
                                "text": " "
                            },
                            {
                                "type": "user",
                                "user_id": "U0331FZS7JT"
                            },
                            {
                                "type": "text",
                                "text": "\n今年入荷分は2kgと聞いてますが、\nそれは別途あるんですよね？"
                            }
                        ]
                    }
                ]
            }
        ]
    },
    {
        "text": "<@U0606SPN4BW>\n<!subteam^S073HEMKWV7|@hirakawa-adachi-yamamoto-fuse> <!subteam^S072Q871SF9|@oka-matsui-furukawa-hayashi-kimura-hasegawa-kawatani> <@U066P20UQH1>\nペガサス大橋様より情報入力エクセルファイル（依頼書）がメールで入っております。\n添付は、分かる部分で入力（緑塗り潰し箇所）したものです。すみませんが、\n念のためご確認と黄色部分の情報入力をお願いできませんでしょうか。",
        "files": [
            {
                "id": "F092Q1ERHL1",
                "created": 1750412885,
                "timestamp": 1750412885,
                "name": "ペガサス_DHL輸入AWB作成+集荷依頼書　EMPTY.xls",
                "title": "ペガサス_DHL輸入AWB作成+集荷依頼書　EMPTY.xls",
                "mimetype": "application\/vnd.ms-excel",
                "filetype": "xls",
                "pretty_type": "Excel Spreadsheet",
                "user": "U05KGS6HN9H",
                "user_team": "T033D70RR6H",
                "editable": false,
                "size": 64000,
                "mode": "hosted",
                "is_external": false,
                "external_type": "",
                "is_public": true,
                "public_url_shared": false,
                "display_as_bot": false,
                "username": "",
                "url_private": "https:\/\/files.slack.com\/files-pri\/T033D70RR6H-F092Q1ERHL1\/_____________dhl______awb_________________________empty.xls?token=xoxe-3115238875221-9710624591398-9697214945543-aa82359f925d11baadb4ddc07b089467",
                "url_private_download": "https:\/\/files.slack.com\/files-pri\/T033D70RR6H-F092Q1ERHL1\/download\/_____________dhl______awb_________________________empty.xls?token=xoxe-3115238875221-9710624591398-9697214945543-aa82359f925d11baadb4ddc07b089467",
                "media_display_type": "unknown",
                "converted_pdf": "https:\/\/files.slack.com\/files-tmb\/T033D70RR6H-F092Q1ERHL1-cc83bfbf21\/_____________dhl______awb_________________________empty_converted.pdf?t=xoxe-3115238875221-9710624591398-9697214945543-aa82359f925d11baadb4ddc07b089467",
                "thumb_pdf": "https:\/\/files.slack.com\/files-tmb\/T033D70RR6H-F092Q1ERHL1-cc83bfbf21\/_____________dhl______awb_________________________empty_thumb_pdf.png?t=xoxe-3115238875221-9710624591398-9697214945543-aa82359f925d11baadb4ddc07b089467",
                "thumb_pdf_w": 909,
                "thumb_pdf_h": 1286,
                "permalink": "https:\/\/grp-ssm9297.slack.com\/files\/U0331FWGQRM\/F092Q1ERHL1\/_____________dhl______awb_________________________empty.xls",
                "permalink_public": "https:\/\/slack-files.com\/T033D70RR6H-F092Q1ERHL1-a4c0d55f3e",
                "is_starred": false,
                "skipped_shares": true,
                "has_rich_preview": false,
                "file_access": "visible"
            }
        ],
        "upload": false,
        "user": "U05KGS6HN9H",
        "display_as_bot": false,
        "blocks": [
            {
                "type": "rich_text",
                "block_id": "V2sh4",
                "elements": [
                    {
                        "type": "rich_text_section",
                        "elements": [
                            {
                                "type": "user",
                                "user_id": "U0606SPN4BW"
                            },
                            {
                                "type": "text",
                                "text": "\n"
                            },
                            {
                                "type": "usergroup",
                                "usergroup_id": "S073HEMKWV7"
                            },
                            {
                                "type": "text",
                                "text": " "
                            },
                            {
                                "type": "usergroup",
                                "usergroup_id": "S072Q871SF9"
                            },
                            {
                                "type": "text",
                                "text": " "
                            },
                            {
                                "type": "user",
                                "user_id": "U066P20UQH1"
                            },
                            {
                                "type": "text",
                                "text": "\nペガサス大橋様より情報入力エクセルファイル（依頼書）がメールで入っております。\n添付は、分かる部分で入力（緑塗り潰し箇所）したものです。すみませんが、\n念のためご確認と黄色部分の情報入力をお願いできませんでしょうか。"
                            }
                        ]
                    }
                ]
            }
        ],
        "type": "message",
        "ts": "1750412915.499169",
        "client_msg_id": "19885125-30ca-4401-8645-a43e8ba00f16",
        "thread_ts": "1746671028.965679",
        "parent_user_id": "U066P20UQH1"
    },
    {
        "user": "U05KGS6HN9H",
        "type": "message",
        "ts": "1750415950.640249",
        "client_msg_id": "7618c7ac-2fe9-44e2-b997-acd94012627f",
        "text": "<@U066P20UQH1> <@U0606SPN4BW>\n<!subteam^S073HEMKWV7|@hirakawa-adachi-yamamoto-fuse> <!subteam^S088LEJ1U5T|@kanayama-fukui-miyoshi-yokoi-takuwa-hara-imaoka-agou>\n本日6\/20のUPSで出荷しました。\nAWB No 1Z219Y8R0400417606\n宜しくお願い致します。",
        "team": "T033D70RR6H",
        "user_team": "T033D70RR6H",
        "source_team": "T033D70RR6H",
        "user_profile": {
            "avatar_hash": "gc4e7258333f",
            "image_72": "https:\/\/secure.gravatar.com\/avatar\/c4e7258333f2958f831d063db85b4542.jpg?s=72&d=https%3A%2F%2Fa.slack-edge.com%2Fdf10d%2Fimg%2Favatars%2Fava_0005-72.png",
            "first_name": "Adachi",
            "real_name": "Adachi",
            "display_name": "足立",
            "team": "T033D70RR6H",
            "name": "tousuien05",
            "is_restricted": false,
            "is_ultra_restricted": false
        },
        "thread_ts": "1749686769.002289",
        "parent_user_id": "U066P20UQH1",
        "blocks": [
            {
                "type": "rich_text",
                "block_id": "+WlPX",
                "elements": [
                    {
                        "type": "rich_text_section",
                        "elements": [
                            {
                                "type": "user",
                                "user_id": "U066P20UQH1"
                            },
                            {
                                "type": "text",
                                "text": " "
                            },
                            {
                                "type": "user",
                                "user_id": "U0606SPN4BW"
                            },
                            {
                                "type": "text",
                                "text": "\n"
                            },
                            {
                                "type": "usergroup",
                                "usergroup_id": "S073HEMKWV7"
                            },
                            {
                                "type": "text",
                                "text": " "
                            },
                            {
                                "type": "usergroup",
                                "usergroup_id": "S088LEJ1U5T"
                            },
                            {
                                "type": "text",
                                "text": "\n本日6\/20のUPSで出荷しました。\nAWB No 1Z219Y8R0400417606\n宜しくお願い致します。"
                            }
                        ]
                    }
                ]
            }
        ],
        "reactions": [
            {
                "name": "連絡完了",
                "users": [
                    "U066P20UQH1"
                ],
                "count": 1
            }
        ]
    },
    {
        "user": "U05KGS6HN9H",
        "type": "message",
        "ts": "1750415966.686229",
        "client_msg_id": "0c357d4e-702f-4d92-94b5-b98de4141863",
        "text": "<@U066P20UQH1> <@U0606SPN4BW>\n<!subteam^S073HEMKWV7|@hirakawa-adachi-yamamoto-fuse> <!subteam^S088LEJ1U5T|@kanayama-fukui-miyoshi-yokoi-takuwa-hara-imaoka-agou>\n本日6\/20のDHLでTSE-MOM-012-25-1を出荷しました。\nAWB No 7007164581\n宜しくお願い致します。",
        "team": "T033D70RR6H",
        "user_team": "T033D70RR6H",
        "source_team": "T033D70RR6H",
        "user_profile": {
            "avatar_hash": "gc4e7258333f",
            "image_72": "https:\/\/secure.gravatar.com\/avatar\/c4e7258333f2958f831d063db85b4542.jpg?s=72&d=https%3A%2F%2Fa.slack-edge.com%2Fdf10d%2Fimg%2Favatars%2Fava_0005-72.png",
            "first_name": "Adachi",
            "real_name": "Adachi",
            "display_name": "足立",
            "team": "T033D70RR6H",
            "name": "tousuien05",
            "is_restricted": false,
            "is_ultra_restricted": false
        },
        "thread_ts": "1748414455.603919",
        "parent_user_id": "U066P20UQH1",
        "blocks": [
            {
                "type": "rich_text",
                "block_id": "ArprQ",
                "elements": [
                    {
                        "type": "rich_text_section",
                        "elements": [
                            {
                                "type": "user",
                                "user_id": "U066P20UQH1"
                            },
                            {
                                "type": "text",
                                "text": " "
                            },
                            {
                                "type": "user",
                                "user_id": "U0606SPN4BW"
                            },
                            {
                                "type": "text",
                                "text": "\n"
                            },
                            {
                                "type": "usergroup",
                                "usergroup_id": "S073HEMKWV7"
                            },
                            {
                                "type": "text",
                                "text": " "
                            },
                            {
                                "type": "usergroup",
                                "usergroup_id": "S088LEJ1U5T"
                            },
                            {
                                "type": "text",
                                "text": "\n本日6\/20のDHLでTSE-MOM-012-25-1を出荷しました。\nAWB No 7007164581\n宜しくお願い致します。"
                            }
                        ]
                    }
                ]
            }
        ]
    },
    {
        "user": "U05KGS6HN9H",
        "type": "message",
        "ts": "1750415979.370079",
        "client_msg_id": "4ba4abe7-a137-4150-88b5-1eebb3edf85a",
        "text": "<@U066P20UQH1>\n<!subteam^S073HEMKWV7|@hirakawa-adachi-yamamoto-fuse> <!subteam^S088LEJ1U5T|@kanayama-fukui-miyoshi-yokoi-takuwa-hara-imaoka-agou>\n本日6\/20のDHLで出荷しました。\nAWB No 7007158686\n宜しくお願い致します。",
        "team": "T033D70RR6H",
        "user_team": "T033D70RR6H",
        "source_team": "T033D70RR6H",
        "user_profile": {
            "avatar_hash": "gc4e7258333f",
            "image_72": "https:\/\/secure.gravatar.com\/avatar\/c4e7258333f2958f831d063db85b4542.jpg?s=72&d=https%3A%2F%2Fa.slack-edge.com%2Fdf10d%2Fimg%2Favatars%2Fava_0005-72.png",
            "first_name": "Adachi",
            "real_name": "Adachi",
            "display_name": "足立",
            "team": "T033D70RR6H",
            "name": "tousuien05",
            "is_restricted": false,
            "is_ultra_restricted": false
        },
        "thread_ts": "1749177242.407219",
        "parent_user_id": "U066P20UQH1",
        "blocks": [
            {
                "type": "rich_text",
                "block_id": "Ni87J",
                "elements": [
                    {
                        "type": "rich_text_section",
                        "elements": [
                            {
                                "type": "user",
                                "user_id": "U066P20UQH1"
                            },
                            {
                                "type": "text",
                                "text": "\n"
                            },
                            {
                                "type": "usergroup",
                                "usergroup_id": "S073HEMKWV7"
                            },
                            {
                                "type": "text",
                                "text": " "
                            },
                            {
                                "type": "usergroup",
                                "usergroup_id": "S088LEJ1U5T"
                            },
                            {
                                "type": "text",
                                "text": "\n本日6\/20のDHLで出荷しました。\nAWB No 7007158686\n宜しくお願い致します。"
                            }
                        ]
                    }
                ]
            }
        ]
    },
    {
        "user": "U05KGS6HN9H",
        "type": "message",
        "ts": "1750415993.243359",
        "client_msg_id": "38c06924-35a8-4443-bfae-ce767e10936b",
        "text": "<@U0331FWGQRM>\n<!subteam^S073HEMKWV7|@hirakawa-adachi-yamamoto-fuse> <!subteam^S088LEJ1U5T|@kanayama-fukui-miyoshi-yokoi-takuwa-hara-imaoka-agou>\n本日のDHLで出荷しました。\nAWB No 7007164500\n宜しくお願い致します。",
        "team": "T033D70RR6H",
        "user_team": "T033D70RR6H",
        "source_team": "T033D70RR6H",
        "user_profile": {
            "avatar_hash": "gc4e7258333f",
            "image_72": "https:\/\/secure.gravatar.com\/avatar\/c4e7258333f2958f831d063db85b4542.jpg?s=72&d=https%3A%2F%2Fa.slack-edge.com%2Fdf10d%2Fimg%2Favatars%2Fava_0005-72.png",
            "first_name": "Adachi",
            "real_name": "Adachi",
            "display_name": "足立",
            "team": "T033D70RR6H",
            "name": "tousuien05",
            "is_restricted": false,
            "is_ultra_restricted": false
        },
        "thread_ts": "1749601892.354139",
        "parent_user_id": "U0331FWGQRM",
        "blocks": [
            {
                "type": "rich_text",
                "block_id": "iVIdQ",
                "elements": [
                    {
                        "type": "rich_text_section",
                        "elements": [
                            {
                                "type": "user",
                                "user_id": "U0331FWGQRM"
                            },
                            {
                                "type": "text",
                                "text": "\n"
                            },
                            {
                                "type": "usergroup",
                                "usergroup_id": "S073HEMKWV7"
                            },
                            {
                                "type": "text",
                                "text": " "
                            },
                            {
                                "type": "usergroup",
                                "usergroup_id": "S088LEJ1U5T"
                            },
                            {
                                "type": "text",
                                "text": "\n本日のDHLで出荷しました。\nAWB No 7007164500\n宜しくお願い致します。"
                            }
                        ]
                    }
                ]
            }
        ]
    },
    {
        "user": "U0331FWGQRM",
        "type": "message",
        "ts": "1750433332.398859",
        "client_msg_id": "13487E64-BE46-4073-87A7-A32414FE5455",
        "text": "<@U0840UVFVA8> <!subteam^S088LEJ1U5T|@kanayama-fukui-miyoshi-yokoi-takuwa-hara-imaoka-agou> <!subteam^S073HEMKWV7|@hirakawa-adachi-yamamoto-fuse> <@U03BLQ65GK0> <@U0331FZS7JT>\nどうなってますか？？\n念のために整理します。下記流れです。\n\n元々の出荷予定日6\/30\n↓\n粉砕後の抹茶の品質悪いのが発覚で7\/15出荷に延期\n↓\nセバスチャンより、\nフレーバー抹茶であれば、粉砕によって退色した抹茶でもいいとのこと。（写真を送って確認済み）\nPure matchaは品質が良い（いつもの品質）のものにしてくれ、とのこと。\n↓\nフレーバー抹茶は6\/30出荷可能？\nPure抹茶の出荷日はいつ？？",
        "team": "T033D70RR6H",
        "user_team": "T033D70RR6H",
        "source_team": "T033D70RR6H",
        "user_profile": {
            "avatar_hash": "gf9d05f2cae1",
            "image_72": "https:\/\/secure.gravatar.com\/avatar\/f9d05f2cae161f657bb1248fc85b5235.jpg?s=72&d=https%3A%2F%2Fa.slack-edge.com%2Fdf10d%2Fimg%2Favatars%2Fava_0008-72.png",
            "first_name": "matsui",
            "real_name": "matsui",
            "display_name": "松井",
            "team": "T033D70RR6H",
            "name": "tousuien.matsui",
            "is_restricted": false,
            "is_ultra_restricted": false
        },
        "thread_ts": "1749485580.376369",
        "parent_user_id": "U0331FWGQRM",
        "blocks": [
            {
                "type": "rich_text",
                "block_id": "LcSs1",
                "elements": [
                    {
                        "type": "rich_text_section",
                        "elements": [
                            {
                                "type": "user",
                                "user_id": "U0840UVFVA8"
                            },
                            {
                                "type": "text",
                                "text": " "
                            },
                            {
                                "type": "usergroup",
                                "usergroup_id": "S088LEJ1U5T"
                            },
                            {
                                "type": "text",
                                "text": " "
                            },
                            {
                                "type": "usergroup",
                                "usergroup_id": "S073HEMKWV7"
                            },
                            {
                                "type": "text",
                                "text": " "
                            },
                            {
                                "type": "user",
                                "user_id": "U03BLQ65GK0"
                            },
                            {
                                "type": "text",
                                "text": " "
                            },
                            {
                                "type": "user",
                                "user_id": "U0331FZS7JT"
                            },
                            {
                                "type": "text",
                                "text": "\nどうなってますか？？\n念のために整理します。下記流れです。\n\n元々の出荷予定日6\/30\n↓\n粉砕後の抹茶の品質悪いのが発覚で7\/15出荷に延期\n↓\nセバスチャンより、\nフレーバー抹茶であれば、粉砕によって退色した抹茶でもいいとのこと。（写真を送って確認済み）\nPure matchaは品質が良い（いつもの品質）のものにしてくれ、とのこと。\n↓\nフレーバー抹茶は6\/30出荷可能？\nPure抹茶の出荷日はいつ？？"
                            }
                        ]
                    }
                ]
            }
        ]
    },
    {
        "user": "U0331FZS7JT",
        "type": "message",
        "ts": "1750453614.454449",
        "edited": {
            "user": "U0331FZS7JT",
            "ts": "1750453718.000000"
        },
        "client_msg_id": "5ba42959-0c13-49df-a830-4359a0671c8e",
        "text": "<@U05KGS6HN9H> <@U041RJKV5JA>\nCC：<!subteam^S072Q871SF9|@oka-matsui-furukawa-hayashi-kimura-hasegawa-kawatani> <!subteam^S088LEJ1U5T|@kanayama-fukui-miyoshi-yokoi-takuwa-hara-imaoka-agou>\n> 今回必要な原料（星峰\/池の白\/星の露）につきまして、星野製茶より原料供給の回答がありました。\n> ①星峰（Yame Grade A）　\n> 　※供給不可\n①ついて、今回の納品分ということですね？\nつまり、星野への年間購入数量の回答ではないという認識ですが間違っています？\n\nもし、年間購入が不可だった場合、\n水宗園の八女碾茶「やぶきた」の最も良い品質のものがかなり良いので、\nこれに焙煎香をつけて対応が可能かと思います。\n※全量焙煎せずに、焙煎したものとしていない色の良い同原料（または八女おくみどりの最も良い品質のもので）でブレンド\n→帰国後、指示出します。",
        "team": "T033D70RR6H",
        "user_team": "T033D70RR6H",
        "source_team": "T033D70RR6H",
        "user_profile": {
            "avatar_hash": "2c9de1514f26",
            "image_72": "https:\/\/avatars.slack-edge.com\/2022-02-16\/3118160981555_2c9de1514f262063f72d_72.png",
            "first_name": "Yuta",
            "real_name": "Yuta Oka",
            "display_name": "岡祐太",
            "team": "T033D70RR6H",
            "name": "yuta.oka.0915",
            "is_restricted": false,
            "is_ultra_restricted": false
        },
        "thread_ts": "1749056559.829009",
        "parent_user_id": "U0331FWGQRM",
        "blocks": [
            {
                "type": "rich_text",
                "block_id": "QP\/zC",
                "elements": [
                    {
                        "type": "rich_text_section",
                        "elements": [
                            {
                                "type": "user",
                                "user_id": "U05KGS6HN9H"
                            },
                            {
                                "type": "text",
                                "text": " "
                            },
                            {
                                "type": "user",
                                "user_id": "U041RJKV5JA"
                            },
                            {
                                "type": "text",
                                "text": "\nCC："
                            },
                            {
                                "type": "usergroup",
                                "usergroup_id": "S072Q871SF9"
                            },
                            {
                                "type": "text",
                                "text": " "
                            },
                            {
                                "type": "usergroup",
                                "usergroup_id": "S088LEJ1U5T"
                            },
                            {
                                "type": "text",
                                "text": "\n"
                            }
                        ]
                    },
                    {
                        "type": "rich_text_quote",
                        "elements": [
                            {
                                "type": "text",
                                "text": "今回必要な原料（星峰\/池の白\/星の露）につきまして、星野製茶より原料供給の回答がありました。\n①星峰（Yame Grade A）　\n　※供給不可"
                            }
                        ]
                    },
                    {
                        "type": "rich_text_section",
                        "elements": [
                            {
                                "type": "text",
                                "text": "①ついて、今回の納品分ということですね？\nつまり、星野への年間購入数量の回答ではないという認識ですが間違っています？\n\nもし、年間購入が不可だった場合、\n水宗園の八女碾茶「やぶきた」の最も良い品質のものがかなり良いので、\nこれに焙煎香をつけて対応が可能かと思います。\n※全量焙煎せずに、焙煎したものとしていない色の良い同原料（または八女おくみどりの最も良い品質のもので）でブレンド\n→帰国後、指示出します。"
                            }
                        ]
                    }
                ]
            }
        ]
    },
    {
        "user": "U0331FZTHEK",
        "type": "message",
        "ts": "1750459981.447419",
        "client_msg_id": "69700653-fa35-4f4a-b5c7-85a94a268e15",
        "text": "<@U08RVRNBY00>\n <!subteam^S073HEMKWV7|@hirakawa-adachi-yamamoto-fuse>\n本件、ご入金を確認致しました。\n・6\/21 [PayPal]\n*034-25*\n・ship      10,000 JPY\n　offset   42,850 JPY\n　total     52,850 JPY\n*035-25*\n・ship      10,000 JPY\n　offset   42,850 JPY\n　total     52,850 JPY\n回収（入金）処理致します。\nよろしくお願いします。",
        "team": "T033D70RR6H",
        "user_team": "T033D70RR6H",
        "source_team": "T033D70RR6H",
        "user_profile": {
            "avatar_hash": "21cdbd6a05f9",
            "image_72": "https:\/\/avatars.slack-edge.com\/2022-02-16\/3115258488741_21cdbd6a05f9a69110f7_72.png",
            "first_name": "Mitsunobu",
            "real_name": "Mitsunobu Katayose",
            "display_name": "片寄",
            "team": "T033D70RR6H",
            "name": "tousuien03",
            "is_restricted": false,
            "is_ultra_restricted": false
        },
        "thread_ts": "1750207822.977079",
        "parent_user_id": "U08RVRNBY00",
        "blocks": [
            {
                "type": "rich_text",
                "block_id": "i2I5S",
                "elements": [
                    {
                        "type": "rich_text_section",
                        "elements": [
                            {
                                "type": "user",
                                "user_id": "U08RVRNBY00"
                            },
                            {
                                "type": "text",
                                "text": "\n "
                            },
                            {
                                "type": "usergroup",
                                "usergroup_id": "S073HEMKWV7"
                            },
                            {
                                "type": "text",
                                "text": "\n本件、ご入金を確認致しました。\n・6\/21 [PayPal]\n"
                            },
                            {
                                "type": "text",
                                "text": "034-25",
                                "style": {
                                    "bold": true
                                }
                            },
                            {
                                "type": "text",
                                "text": "\n・ship      10,000 JPY\n　offset   42,850 JPY\n　total     52,850 JPY\n"
                            },
                            {
                                "type": "text",
                                "text": "035-25",
                                "style": {
                                    "bold": true
                                }
                            },
                            {
                                "type": "text",
                                "text": "\n・ship      10,000 JPY\n　offset   42,850 JPY\n　total     52,850 JPY\n回収（入金）処理致します。\nよろしくお願いします。"
                            }
                        ]
                    }
                ]
            }
        ],
        "reactions": [
            {
                "name": "ありかとう",
                "users": [
                    "U08RVRNBY00"
                ],
                "count": 1
            },
            {
                "name": "入金完了",
                "users": [
                    "U0331FZTHEK"
                ],
                "count": 1
            }
        ]
    },
    {
        "user": "U033G4KN4TD",
        "type": "message",
        "ts": "1750460111.189719",
        "client_msg_id": "897e5b9e-b49e-43f2-889c-6faf4a2199bf",
        "text": "<@U0331FWGQRM> <!subteam^S073HEMKWV7|@hirakawa-adachi-yamamoto-fuse> <!subteam^S088LEJ1U5T|@kanayama-fukui-miyoshi-yokoi-takuwa-hara-imaoka-agou>\n*出荷可能日：7月10日（*フレーバー抹茶・Pure抹茶併せて）\n\nフレーバーの合組：6\/23-24\nPUREの合組：6\/24-25\n外注へ6\/26-7\/4の間で小分け加工依頼（一部桃翠園にて小分け）\n→7\/7-7\/8で外注先→桃翠園へ納品\n7\/8-9で梱包予定\n\n上記予定が最短となります。\nよろしくお願いいたします。",
        "team": "T033D70RR6H",
        "user_team": "T033D70RR6H",
        "source_team": "T033D70RR6H",
        "user_profile": {
            "avatar_hash": "b87877677a67",
            "image_72": "https:\/\/avatars.slack-edge.com\/2022-02-16\/3118194883458_b87877677a672efe50f6_72.png",
            "first_name": "Fukui",
            "real_name": "Fukui",
            "display_name": "福井",
            "team": "T033D70RR6H",
            "name": "tousuien04",
            "is_restricted": false,
            "is_ultra_restricted": false
        },
        "thread_ts": "1749485580.376369",
        "parent_user_id": "U0331FWGQRM",
        "blocks": [
            {
                "type": "rich_text",
                "block_id": "kGZWx",
                "elements": [
                    {
                        "type": "rich_text_section",
                        "elements": [
                            {
                                "type": "user",
                                "user_id": "U0331FWGQRM"
                            },
                            {
                                "type": "text",
                                "text": " "
                            },
                            {
                                "type": "usergroup",
                                "usergroup_id": "S073HEMKWV7"
                            },
                            {
                                "type": "text",
                                "text": " "
                            },
                            {
                                "type": "usergroup",
                                "usergroup_id": "S088LEJ1U5T"
                            },
                            {
                                "type": "text",
                                "text": "\n"
                            },
                            {
                                "type": "text",
                                "text": "出荷可能日：7月10日（",
                                "style": {
                                    "bold": true
                                }
                            },
                            {
                                "type": "text",
                                "text": "フレーバー抹茶・Pure抹茶併せて）\n\nフレーバーの合組：6\/23-24\nPUREの合組：6\/24-25\n外注へ6\/26-7\/4の間で小分け加工依頼（一部桃翠園にて小分け）\n→7\/7-7\/8で外注先→桃翠園へ納品\n7\/8-9で梱包予定\n\n上記予定が最短となります。\nよろしくお願いいたします。"
                            }
                        ]
                    }
                ]
            }
        ]
    },
    {
        "user": "U041RJKV5JA",
        "type": "message",
        "ts": "1750463962.333199",
        "client_msg_id": "b72c9cf6-abad-48b6-a5ed-9591ccd48982",
        "text": "<@U0331FWGQRM>\n <!subteam^S073HEMKWV7|@hirakawa-adachi-yamamoto-fuse> <@U0331FZTHEK>\n本件につきまして、出荷予定日である6月初旬を過ぎておりますが、現時点での出荷日はまだ未定でしょうか。",
        "team": "T033D70RR6H",
        "user_team": "T033D70RR6H",
        "source_team": "T033D70RR6H",
        "user_profile": {
            "avatar_hash": "aed9eafd9eee",
            "image_72": "https:\/\/avatars.slack-edge.com\/2022-09-11\/4078874890257_aed9eafd9eee277ba076_72.png",
            "first_name": "Hirakawa",
            "real_name": "Hirakawa",
            "display_name": "平川",
            "team": "T033D70RR6H",
            "name": "tousuien.s006",
            "is_restricted": false,
            "is_ultra_restricted": false
        },
        "thread_ts": "1743746591.532039",
        "parent_user_id": "U0331FWGQRM",
        "blocks": [
            {
                "type": "rich_text",
                "block_id": "btLR5",
                "elements": [
                    {
                        "type": "rich_text_section",
                        "elements": [
                            {
                                "type": "user",
                                "user_id": "U0331FWGQRM"
                            },
                            {
                                "type": "text",
                                "text": "\n "
                            },
                            {
                                "type": "usergroup",
                                "usergroup_id": "S073HEMKWV7"
                            },
                            {
                                "type": "text",
                                "text": " "
                            },
                            {
                                "type": "user",
                                "user_id": "U0331FZTHEK"
                            },
                            {
                                "type": "text",
                                "text": "\n本件につきまして、出荷予定日である6月初旬を過ぎておりますが、現時点での出荷日はまだ未定でしょうか。"
                            }
                        ]
                    }
                ]
            }
        ]
    },
    {
        "user": "U066P20UQH1",
        "type": "message",
        "ts": "1750465576.099039",
        "client_msg_id": "e2c369d7-fa00-46de-9bf6-10f858433864",
        "text": "<!subteam^S088LEJ1U5T|@kanayama-fukui-miyoshi-yokoi-takuwa-hara-imaoka-agou> <!subteam^S073HEMKWV7|@hirakawa-adachi-yamamoto-fuse>\nお客さんから50gに小分けした場合は7月中頃出荷になってしまうと伝えたところ、1kgを今月中に出荷で良いと連絡をいただきましたので、ご対応お願いいたします。\n\n<!subteam^S08NN8M4LAZ|@katayose-kamiya>\nPayPalにて差額USD 828.28を返金しました。ご認識をお願いいたします。",
        "team": "T033D70RR6H",
        "user_team": "T033D70RR6H",
        "source_team": "T033D70RR6H",
        "user_profile": {
            "avatar_hash": "179323cb3551",
            "image_72": "https:\/\/avatars.slack-edge.com\/2024-04-12\/6955353714228_179323cb3551f7c8ecfe_72.png",
            "first_name": "Haruka",
            "real_name": "Haruka Hayashi",
            "display_name": "林遥香",
            "team": "T033D70RR6H",
            "name": "haru.nboc",
            "is_restricted": false,
            "is_ultra_restricted": false
        },
        "thread_ts": "1746084267.674049",
        "parent_user_id": "U066P20UQH1",
        "blocks": [
            {
                "type": "rich_text",
                "block_id": "uyQ3J",
                "elements": [
                    {
                        "type": "rich_text_section",
                        "elements": [
                            {
                                "type": "usergroup",
                                "usergroup_id": "S088LEJ1U5T"
                            },
                            {
                                "type": "text",
                                "text": " "
                            },
                            {
                                "type": "usergroup",
                                "usergroup_id": "S073HEMKWV7"
                            },
                            {
                                "type": "text",
                                "text": "\nお客さんから50gに小分けした場合は7月中頃出荷になってしまうと伝えたところ、1kgを今月中に出荷で良いと連絡をいただきましたので、ご対応お願いいたします。\n\n"
                            },
                            {
                                "type": "usergroup",
                                "usergroup_id": "S08NN8M4LAZ"
                            },
                            {
                                "type": "text",
                                "text": "\nPayPalにて差額USD 828.28を返金しました。ご認識をお願いいたします。"
                            }
                        ]
                    }
                ]
            }
        ],
        "reactions": [
            {
                "name": "承知_致しました",
                "users": [
                    "U0840UVFVA8"
                ],
                "count": 1
            }
        ]
    },
    {
        "user": "U066P20UQH1",
        "type": "message",
        "ts": "1750466022.708059",
        "client_msg_id": "fdb5547c-0412-4d89-af7c-7cb6124541f9",
        "text": "<!subteam^S088LEJ1U5T|@kanayama-fukui-miyoshi-yokoi-takuwa-hara-imaoka-agou> <!subteam^S073HEMKWV7|@hirakawa-adachi-yamamoto-fuse>\nお客様からほうじ茶の出荷予定日について確認の連絡が来ております、ご確認お願いいたします:woman-bowing:",
        "team": "T033D70RR6H",
        "user_team": "T033D70RR6H",
        "source_team": "T033D70RR6H",
        "user_profile": {
            "avatar_hash": "179323cb3551",
            "image_72": "https:\/\/avatars.slack-edge.com\/2024-04-12\/6955353714228_179323cb3551f7c8ecfe_72.png",
            "first_name": "Haruka",
            "real_name": "Haruka Hayashi",
            "display_name": "林遥香",
            "team": "T033D70RR6H",
            "name": "haru.nboc",
            "is_restricted": false,
            "is_ultra_restricted": false
        },
        "thread_ts": "1746671028.965679",
        "parent_user_id": "U066P20UQH1",
        "blocks": [
            {
                "type": "rich_text",
                "block_id": "9ICoE",
                "elements": [
                    {
                        "type": "rich_text_section",
                        "elements": [
                            {
                                "type": "usergroup",
                                "usergroup_id": "S088LEJ1U5T"
                            },
                            {
                                "type": "text",
                                "text": " "
                            },
                            {
                                "type": "usergroup",
                                "usergroup_id": "S073HEMKWV7"
                            },
                            {
                                "type": "text",
                                "text": "\nお客様からほうじ茶の出荷予定日について確認の連絡が来ております、ご確認お願いいたします"
                            },
                            {
                                "type": "emoji",
                                "name": "woman-bowing",
                                "unicode": "1f647-200d-2640-fe0f"
                            }
                        ]
                    }
                ]
            }
        ]
    },
    {
        "user": "U033G4KN4TD",
        "type": "message",
        "ts": "1750466362.153809",
        "edited": {
            "user": "U033G4KN4TD",
            "ts": "1750466588.000000"
        },
        "client_msg_id": "77c37531-89e0-4bbc-96d0-41f87d83e5e8",
        "text": "<@U0331FWGQRM> <!subteam^S073HEMKWV7|@hirakawa-adachi-yamamoto-fuse> <!subteam^S088LEJ1U5T|@kanayama-fukui-miyoshi-yokoi-takuwa-hara-imaoka-agou>\n缶の入荷が6\/23であれば出荷可能です。\n6\/24以降入荷の場合はまた相談させてください。\nよろしくお願いいたします。",
        "team": "T033D70RR6H",
        "user_team": "T033D70RR6H",
        "source_team": "T033D70RR6H",
        "user_profile": {
            "avatar_hash": "b87877677a67",
            "image_72": "https:\/\/avatars.slack-edge.com\/2022-02-16\/3118194883458_b87877677a672efe50f6_72.png",
            "first_name": "Fukui",
            "real_name": "Fukui",
            "display_name": "福井",
            "team": "T033D70RR6H",
            "name": "tousuien04",
            "is_restricted": false,
            "is_ultra_restricted": false
        },
        "thread_ts": "1747126757.485039",
        "parent_user_id": "U0331FWGQRM",
        "blocks": [
            {
                "type": "rich_text",
                "block_id": "yazCK",
                "elements": [
                    {
                        "type": "rich_text_section",
                        "elements": [
                            {
                                "type": "user",
                                "user_id": "U0331FWGQRM"
                            },
                            {
                                "type": "text",
                                "text": " "
                            },
                            {
                                "type": "usergroup",
                                "usergroup_id": "S073HEMKWV7"
                            },
                            {
                                "type": "text",
                                "text": " "
                            },
                            {
                                "type": "usergroup",
                                "usergroup_id": "S088LEJ1U5T"
                            },
                            {
                                "type": "text",
                                "text": "\n缶の入荷が6\/23であれば出荷可能です。\n6\/24以降入荷の場合はまた相談させてください。\nよろしくお願いいたします。"
                            }
                        ]
                    }
                ]
            }
        ]
    },
    {
        "user": "U0331FZTHEK",
        "type": "message",
        "ts": "1750467647.719019",
        "client_msg_id": "0dc73ae8-22eb-4646-8275-96833a072f6b",
        "text": "<@U066P20UQH1>\n <!subteam^S073HEMKWV7|@hirakawa-adachi-yamamoto-fuse>\nご返金を確認致しました。\n・6\/21 [PayPal]\n・△828.28 USD\n返金伝票処理致します。\nよろしくお願いします。",
        "team": "T033D70RR6H",
        "user_team": "T033D70RR6H",
        "source_team": "T033D70RR6H",
        "user_profile": {
            "avatar_hash": "21cdbd6a05f9",
            "image_72": "https:\/\/avatars.slack-edge.com\/2022-02-16\/3115258488741_21cdbd6a05f9a69110f7_72.png",
            "first_name": "Mitsunobu",
            "real_name": "Mitsunobu Katayose",
            "display_name": "片寄",
            "team": "T033D70RR6H",
            "name": "tousuien03",
            "is_restricted": false,
            "is_ultra_restricted": false
        },
        "thread_ts": "1746084267.674049",
        "parent_user_id": "U066P20UQH1",
        "blocks": [
            {
                "type": "rich_text",
                "block_id": "8WZUv",
                "elements": [
                    {
                        "type": "rich_text_section",
                        "elements": [
                            {
                                "type": "user",
                                "user_id": "U066P20UQH1"
                            },
                            {
                                "type": "text",
                                "text": "\n "
                            },
                            {
                                "type": "usergroup",
                                "usergroup_id": "S073HEMKWV7"
                            },
                            {
                                "type": "text",
                                "text": "\nご返金を確認致しました。\n・6\/21 [PayPal]\n・△828.28 USD\n返金伝票処理致します。\nよろしくお願いします。"
                            }
                        ]
                    }
                ]
            }
        ],
        "reactions": [
            {
                "name": "pray",
                "users": [
                    "U066P20UQH1"
                ],
                "count": 1
            }
        ]
    },
    {
        "user": "U033G4KN4TD",
        "type": "message",
        "ts": "1750468419.406309",
        "client_msg_id": "479f042c-941c-40ec-98b7-88edd53eeb24",
        "text": "<@U066P20UQH1> <!subteam^S073HEMKWV7|@hirakawa-adachi-yamamoto-fuse> <!subteam^S088LEJ1U5T|@kanayama-fukui-miyoshi-yokoi-takuwa-hara-imaoka-agou>\nほうじ茶パウダーのみでしたら、7月2日出荷可能です。\nよろしくお願いいたします。",
        "team": "T033D70RR6H",
        "user_team": "T033D70RR6H",
        "source_team": "T033D70RR6H",
        "user_profile": {
            "avatar_hash": "b87877677a67",
            "image_72": "https:\/\/avatars.slack-edge.com\/2022-02-16\/3118194883458_b87877677a672efe50f6_72.png",
            "first_name": "Fukui",
            "real_name": "Fukui",
            "display_name": "福井",
            "team": "T033D70RR6H",
            "name": "tousuien04",
            "is_restricted": false,
            "is_ultra_restricted": false
        },
        "thread_ts": "1746671028.965679",
        "parent_user_id": "U066P20UQH1",
        "blocks": [
            {
                "type": "rich_text",
                "block_id": "24TwF",
                "elements": [
                    {
                        "type": "rich_text_section",
                        "elements": [
                            {
                                "type": "user",
                                "user_id": "U066P20UQH1"
                            },
                            {
                                "type": "text",
                                "text": " "
                            },
                            {
                                "type": "usergroup",
                                "usergroup_id": "S073HEMKWV7"
                            },
                            {
                                "type": "text",
                                "text": " "
                            },
                            {
                                "type": "usergroup",
                                "usergroup_id": "S088LEJ1U5T"
                            },
                            {
                                "type": "text",
                                "text": "\nほうじ茶パウダーのみでしたら、7月2日出荷可能です。\nよろしくお願いいたします。"
                            }
                        ]
                    }
                ]
            }
        ],
        "reactions": [
            {
                "name": "承知-1",
                "users": [
                    "U066P20UQH1"
                ],
                "count": 1
            }
        ]
    },
    {
        "user": "U033G4KN4TD",
        "type": "message",
        "ts": "1750470995.348549",
        "client_msg_id": "3d8bbe1a-de5a-4a0d-98a8-7be2e822ec53",
        "text": "<@U0606SPN4BW> <!subteam^S073HEMKWV7|@hirakawa-adachi-yamamoto-fuse>\n静岡製缶の30ｇ缶ですが、在庫が42缶のため\n全量中国缶の使用でよろしいでしょうか。\nご確認お願いいたします。",
        "team": "T033D70RR6H",
        "user_team": "T033D70RR6H",
        "source_team": "T033D70RR6H",
        "user_profile": {
            "avatar_hash": "b87877677a67",
            "image_72": "https:\/\/avatars.slack-edge.com\/2022-02-16\/3118194883458_b87877677a672efe50f6_72.png",
            "first_name": "Fukui",
            "real_name": "Fukui",
            "display_name": "福井",
            "team": "T033D70RR6H",
            "name": "tousuien04",
            "is_restricted": false,
            "is_ultra_restricted": false
        },
        "thread_ts": "1745625400.900269",
        "parent_user_id": "U0606SPN4BW",
        "blocks": [
            {
                "type": "rich_text",
                "block_id": "cEil5",
                "elements": [
                    {
                        "type": "rich_text_section",
                        "elements": [
                            {
                                "type": "user",
                                "user_id": "U0606SPN4BW"
                            },
                            {
                                "type": "text",
                                "text": " "
                            },
                            {
                                "type": "usergroup",
                                "usergroup_id": "S073HEMKWV7"
                            },
                            {
                                "type": "text",
                                "text": "\n静岡製缶の30ｇ缶ですが、在庫が42缶のため\n全量中国缶の使用でよろしいでしょうか。\nご確認お願いいたします。"
                            }
                        ]
                    }
                ]
            }
        ]
    },
    {
        "user": "U033G4KN4TD",
        "type": "message",
        "ts": "1750478909.863079",
        "client_msg_id": "4805afcf-852d-4176-8e89-6a86c3e0b7bd",
        "text": "<@U0331FWGQRM> <!subteam^S073HEMKWV7|@hirakawa-adachi-yamamoto-fuse> <!subteam^S088LEJ1U5T|@kanayama-fukui-miyoshi-yokoi-takuwa-hara-imaoka-agou>\n製造：7月1日\n\n <@U05KGS6HN9H> 7\/2以降検疫予定確認後、出荷可能日の連絡を\nお願いいたします。",
        "team": "T033D70RR6H",
        "user_team": "T033D70RR6H",
        "source_team": "T033D70RR6H",
        "user_profile": {
            "avatar_hash": "b87877677a67",
            "image_72": "https:\/\/avatars.slack-edge.com\/2022-02-16\/3118194883458_b87877677a672efe50f6_72.png",
            "first_name": "Fukui",
            "real_name": "Fukui",
            "display_name": "福井",
            "team": "T033D70RR6H",
            "name": "tousuien04",
            "is_restricted": false,
            "is_ultra_restricted": false
        },
        "thread_ts": "1746022167.543959",
        "parent_user_id": "U0331FWGQRM",
        "blocks": [
            {
                "type": "rich_text",
                "block_id": "hksG3",
                "elements": [
                    {
                        "type": "rich_text_section",
                        "elements": [
                            {
                                "type": "user",
                                "user_id": "U0331FWGQRM"
                            },
                            {
                                "type": "text",
                                "text": " "
                            },
                            {
                                "type": "usergroup",
                                "usergroup_id": "S073HEMKWV7"
                            },
                            {
                                "type": "text",
                                "text": " "
                            },
                            {
                                "type": "usergroup",
                                "usergroup_id": "S088LEJ1U5T"
                            },
                            {
                                "type": "text",
                                "text": "\n製造：7月1日\n\n "
                            },
                            {
                                "type": "user",
                                "user_id": "U05KGS6HN9H"
                            },
                            {
                                "type": "text",
                                "text": " 7\/2以降検疫予定確認後、出荷可能日の連絡を\nお願いいたします。"
                            }
                        ]
                    }
                ]
            }
        ]
    },
    {
        "user": "U033G4KN4TD",
        "type": "message",
        "ts": "1750478926.719039",
        "client_msg_id": "8d1f4cd9-7424-4858-bc4c-425db0a13e77",
        "text": "<@U0331FWGQRM> <!subteam^S073HEMKWV7|@hirakawa-adachi-yamamoto-fuse> <!subteam^S088LEJ1U5T|@kanayama-fukui-miyoshi-yokoi-takuwa-hara-imaoka-agou>\n製造：7月1日\n\n <@U05KGS6HN9H> 7\/2以降検疫予定確認後、出荷可能日の連絡を\nお願いいたします。",
        "team": "T033D70RR6H",
        "user_team": "T033D70RR6H",
        "source_team": "T033D70RR6H",
        "user_profile": {
            "avatar_hash": "b87877677a67",
            "image_72": "https:\/\/avatars.slack-edge.com\/2022-02-16\/3118194883458_b87877677a672efe50f6_72.png",
            "first_name": "Fukui",
            "real_name": "Fukui",
            "display_name": "福井",
            "team": "T033D70RR6H",
            "name": "tousuien04",
            "is_restricted": false,
            "is_ultra_restricted": false
        },
        "thread_ts": "1747161488.518429",
        "parent_user_id": "U0331FWGQRM",
        "blocks": [
            {
                "type": "rich_text",
                "block_id": "hksG3",
                "elements": [
                    {
                        "type": "rich_text_section",
                        "elements": [
                            {
                                "type": "user",
                                "user_id": "U0331FWGQRM"
                            },
                            {
                                "type": "text",
                                "text": " "
                            },
                            {
                                "type": "usergroup",
                                "usergroup_id": "S073HEMKWV7"
                            },
                            {
                                "type": "text",
                                "text": " "
                            },
                            {
                                "type": "usergroup",
                                "usergroup_id": "S088LEJ1U5T"
                            },
                            {
                                "type": "text",
                                "text": "\n製造：7月1日\n\n "
                            },
                            {
                                "type": "user",
                                "user_id": "U05KGS6HN9H"
                            },
                            {
                                "type": "text",
                                "text": " 7\/2以降検疫予定確認後、出荷可能日の連絡を\nお願いいたします。"
                            }
                        ]
                    }
                ]
            }
        ]
    },
    {
        "user": "U033G4KN4TD",
        "type": "message",
        "ts": "1750479012.355529",
        "client_msg_id": "ee8e832a-c852-4ba7-80f2-36f3cdc7f73d",
        "text": "<@U08RVRNBY00> <@U0331FWGQRM> <!subteam^S073HEMKWV7|@hirakawa-adachi-yamamoto-fuse> <!subteam^S088LEJ1U5T|@kanayama-fukui-miyoshi-yokoi-takuwa-hara-imaoka-agou>\nTSE-TAC-034-25\nTSE-TAC-035-25\n\n*製造：7月1日*\n\n <@U05KGS6HN9H> 7\/2以降検疫予定確認後、出荷可能日の連絡を\nお願いいたします。",
        "team": "T033D70RR6H",
        "user_team": "T033D70RR6H",
        "source_team": "T033D70RR6H",
        "user_profile": {
            "avatar_hash": "b87877677a67",
            "image_72": "https:\/\/avatars.slack-edge.com\/2022-02-16\/3118194883458_b87877677a672efe50f6_72.png",
            "first_name": "Fukui",
            "real_name": "Fukui",
            "display_name": "福井",
            "team": "T033D70RR6H",
            "name": "tousuien04",
            "is_restricted": false,
            "is_ultra_restricted": false
        },
        "thread_ts": "1750207822.977079",
        "parent_user_id": "U08RVRNBY00",
        "blocks": [
            {
                "type": "rich_text",
                "block_id": "BIfNs",
                "elements": [
                    {
                        "type": "rich_text_section",
                        "elements": [
                            {
                                "type": "user",
                                "user_id": "U08RVRNBY00"
                            },
                            {
                                "type": "text",
                                "text": " "
                            },
                            {
                                "type": "user",
                                "user_id": "U0331FWGQRM"
                            },
                            {
                                "type": "text",
                                "text": " "
                            },
                            {
                                "type": "usergroup",
                                "usergroup_id": "S073HEMKWV7"
                            },
                            {
                                "type": "text",
                                "text": " "
                            },
                            {
                                "type": "usergroup",
                                "usergroup_id": "S088LEJ1U5T"
                            },
                            {
                                "type": "text",
                                "text": "\nTSE-TAC-034-25\nTSE-TAC-035-25\n\n"
                            },
                            {
                                "type": "text",
                                "text": "製造：7月1日",
                                "style": {
                                    "bold": true
                                }
                            },
                            {
                                "type": "text",
                                "text": "\n\n "
                            },
                            {
                                "type": "user",
                                "user_id": "U05KGS6HN9H"
                            },
                            {
                                "type": "text",
                                "text": " 7\/2以降検疫予定確認後、出荷可能日の連絡を\nお願いいたします。"
                            }
                        ]
                    }
                ]
            }
        ]
    },
    {
        "user": "U05KGS6HN9H",
        "type": "message",
        "ts": "1750482612.500799",
        "edited": {
            "user": "U05KGS6HN9H",
            "ts": "1750482746.000000"
        },
        "client_msg_id": "0f7270ce-b17e-4c22-9e52-d4322f04b7af",
        "text": "<@U0331FWGQRM>\n<!subteam^S073HEMKWV7|@hirakawa-adachi-yamamoto-fuse> <!subteam^S088LEJ1U5T|@kanayama-fukui-miyoshi-yokoi-takuwa-hara-imaoka-agou>\nボールミル状況が固まりました。\n出荷可能日　7\/4（金）にてお願い致します。\n《概要》\n7\/1　　作業完了\n7\/2-3　検疫検査（未申請の為、仮予定）\n7\/3-4　証明書取得\n7\/4　出荷",
        "team": "T033D70RR6H",
        "user_team": "T033D70RR6H",
        "source_team": "T033D70RR6H",
        "user_profile": {
            "avatar_hash": "gc4e7258333f",
            "image_72": "https:\/\/secure.gravatar.com\/avatar\/c4e7258333f2958f831d063db85b4542.jpg?s=72&d=https%3A%2F%2Fa.slack-edge.com%2Fdf10d%2Fimg%2Favatars%2Fava_0005-72.png",
            "first_name": "Adachi",
            "real_name": "Adachi",
            "display_name": "足立",
            "team": "T033D70RR6H",
            "name": "tousuien05",
            "is_restricted": false,
            "is_ultra_restricted": false
        },
        "thread_ts": "1746022167.543959",
        "parent_user_id": "U0331FWGQRM",
        "blocks": [
            {
                "type": "rich_text",
                "block_id": "aPjVP",
                "elements": [
                    {
                        "type": "rich_text_section",
                        "elements": [
                            {
                                "type": "user",
                                "user_id": "U0331FWGQRM"
                            },
                            {
                                "type": "text",
                                "text": "\n"
                            },
                            {
                                "type": "usergroup",
                                "usergroup_id": "S073HEMKWV7"
                            },
                            {
                                "type": "text",
                                "text": " "
                            },
                            {
                                "type": "usergroup",
                                "usergroup_id": "S088LEJ1U5T"
                            },
                            {
                                "type": "text",
                                "text": "\nボールミル状況が固まりました。\n出荷可能日　7\/4（金）にてお願い致します。\n《概要》\n7\/1　　作業完了\n7\/2-3　検疫検査（未申請の為、仮予定）\n7\/3-4　証明書取得\n7\/4　出荷"
                            }
                        ]
                    }
                ]
            }
        ]
    },
    {
        "user": "U05KGS6HN9H",
        "type": "message",
        "ts": "1750482624.705609",
        "edited": {
            "user": "U05KGS6HN9H",
            "ts": "1750482764.000000"
        },
        "client_msg_id": "f7955124-06ba-4521-aba1-b6dd878596f0",
        "text": "<@U0331FWGQRM>\n<!subteam^S073HEMKWV7|@hirakawa-adachi-yamamoto-fuse> <!subteam^S088LEJ1U5T|@kanayama-fukui-miyoshi-yokoi-takuwa-hara-imaoka-agou>\nボールミル状況が固まりました。\n出荷可能日　7\/4（金）にてお願い致します。\n《概要》\n7\/1　　作業完了\n7\/2-3　検疫検査（未申請の為、仮予定）\n7\/3-4　証明書取得\n7\/4　出荷",
        "team": "T033D70RR6H",
        "user_team": "T033D70RR6H",
        "source_team": "T033D70RR6H",
        "user_profile": {
            "avatar_hash": "gc4e7258333f",
            "image_72": "https:\/\/secure.gravatar.com\/avatar\/c4e7258333f2958f831d063db85b4542.jpg?s=72&d=https%3A%2F%2Fa.slack-edge.com%2Fdf10d%2Fimg%2Favatars%2Fava_0005-72.png",
            "first_name": "Adachi",
            "real_name": "Adachi",
            "display_name": "足立",
            "team": "T033D70RR6H",
            "name": "tousuien05",
            "is_restricted": false,
            "is_ultra_restricted": false
        },
        "thread_ts": "1747161488.518429",
        "parent_user_id": "U0331FWGQRM",
        "blocks": [
            {
                "type": "rich_text",
                "block_id": "aPjVP",
                "elements": [
                    {
                        "type": "rich_text_section",
                        "elements": [
                            {
                                "type": "user",
                                "user_id": "U0331FWGQRM"
                            },
                            {
                                "type": "text",
                                "text": "\n"
                            },
                            {
                                "type": "usergroup",
                                "usergroup_id": "S073HEMKWV7"
                            },
                            {
                                "type": "text",
                                "text": " "
                            },
                            {
                                "type": "usergroup",
                                "usergroup_id": "S088LEJ1U5T"
                            },
                            {
                                "type": "text",
                                "text": "\nボールミル状況が固まりました。\n出荷可能日　7\/4（金）にてお願い致します。\n《概要》\n7\/1　　作業完了\n7\/2-3　検疫検査（未申請の為、仮予定）\n7\/3-4　証明書取得\n7\/4　出荷"
                            }
                        ]
                    }
                ]
            }
        ]
    },
    {
        "user": "U05KGS6HN9H",
        "type": "message",
        "ts": "1750484444.102179",
        "client_msg_id": "e8093f03-6f6b-4d77-8b48-f16666be9f4e",
        "text": "<@U0331FWGQRM>\n<!subteam^S073HEMKWV7|@hirakawa-adachi-yamamoto-fuse> <!subteam^S088LEJ1U5T|@kanayama-fukui-miyoshi-yokoi-takuwa-hara-imaoka-agou>\nTSE-TAC-034-25 及び TSE-TAC-035-25 共に\n出荷可能日　7\/4（金）にてお願い致します。\n《概要》\n7\/1 作業完了\n7\/2-3　検疫検査（未申請の為、仮予定）\n7\/3-4　証明書取得\n7\/4　出荷",
        "team": "T033D70RR6H",
        "user_team": "T033D70RR6H",
        "source_team": "T033D70RR6H",
        "user_profile": {
            "avatar_hash": "gc4e7258333f",
            "image_72": "https:\/\/secure.gravatar.com\/avatar\/c4e7258333f2958f831d063db85b4542.jpg?s=72&d=https%3A%2F%2Fa.slack-edge.com%2Fdf10d%2Fimg%2Favatars%2Fava_0005-72.png",
            "first_name": "Adachi",
            "real_name": "Adachi",
            "display_name": "足立",
            "team": "T033D70RR6H",
            "name": "tousuien05",
            "is_restricted": false,
            "is_ultra_restricted": false
        },
        "thread_ts": "1750207822.977079",
        "parent_user_id": "U08RVRNBY00",
        "blocks": [
            {
                "type": "rich_text",
                "block_id": "EV2ac",
                "elements": [
                    {
                        "type": "rich_text_section",
                        "elements": [
                            {
                                "type": "user",
                                "user_id": "U0331FWGQRM"
                            },
                            {
                                "type": "text",
                                "text": "\n"
                            },
                            {
                                "type": "usergroup",
                                "usergroup_id": "S073HEMKWV7"
                            },
                            {
                                "type": "text",
                                "text": " "
                            },
                            {
                                "type": "usergroup",
                                "usergroup_id": "S088LEJ1U5T"
                            },
                            {
                                "type": "text",
                                "text": "\nTSE-TAC-034-25 及び TSE-TAC-035-25 共に\n出荷可能日　7\/4（金）にてお願い致します。\n《概要》\n7\/1 作業完了\n7\/2-3　検疫検査（未申請の為、仮予定）\n7\/3-4　証明書取得\n7\/4　出荷"
                            }
                        ]
                    }
                ]
            }
        ],
        "reactions": [
            {
                "name": "ありかとう",
                "users": [
                    "U08RVRNBY00"
                ],
                "count": 1
            }
        ]
    }
]